Workbook

Sheet Fotografia
A1: Equipe | B1: 1 - Mês | C1: 2 - Meses | D1: 3 - Meses | E1: Cliente Novo | F1: Comprando | G1: Total Geral
A2: F_Juazeiro | B2: 82 | C2: 30 | D2: 22 | E2: 0 | F2: 106 | G2: 240
A3: F_Maranhão | B3: 7 | C3: 1 | D3: 6 | E3: 0 | F3: 111 | G3: 125
A4: F_Mossoró | B4: 13 | C4: 4 | D4: 18 | E4: 0 | F4: 22 | G4: 57
A5: F_Pernambuco_AS | B5: 17 | C5: 0 | D5: 1 | F5: 5 | G5: 23
A6: F_Pernambuco_PB | B6: 1 | C6: 0 | D6: 5 | F6: 0 | G6: 6
A7: F_Pernambuco_VA | B7: 13 | C7: 3 | D7: 10 | E7: 0 | F7: 9 | G7: 35
A8: F_Sobral | B8: 243 | C8: 52 | D8: 77 | E8: 4 | F8: 308 | G8: 684
A9: F_Teresina | B9: 84 | C9: 7 | D9: 40 | F9: 111 | G9: 242
A10: M_Capital | B10: 337 | C10: 69 | D10: 113 | E10: 1 | F10: 371 | G10: 891
A11: M_Interior | B11: 31 | C11: 4 | D11: 14 | E11: 1 | F11: 133 | G11: 183
A12: M_Nacionais | B12: 73 | C12: 7 | D12: 24 | E12: 0 | F12: 355 | G12: 459
A13: M_Regionais | B13: 67 | C13: 0 | D13: 2 | E13: 0 | F13: 272 | G13: 341
A14: Marujinho | B14: 29 | C14: 7 | D14: 14 | F14: 335 | G14: 385
A15: Telemarketing | B15: 69 | C15: 23 | D15: 14 | E15: 2 | F15: 110 | G15: 218
A16: Total Geral | B16: 1066 | C16: 207 | D16: 360 | E16: 8 | F16: 2248 | G16: 3889

Sheet Resumo Clientes
A1: ativo | B1: Y
A2: Status Equipamento | B2: (Vários itens)
A4: supervisor | B4: vendedor | C4: cod_cliente | D4: nome_fantasia | E4: data_cadastro | F4: Soma de Horizontal | G4: Soma de Vertical | H4: Soma de Total Equipamento
A5: F_Juazeiro | B5: Jefferson | C5: C03266 | D5: FARMACIA SANTA LUZIA | E5: 45688 | F5: 0 | G5: 0 | H5: 0
A6: F_Juazeiro | B6: Jefferson | C6: C03329 | D6: RAIMUNDO JOSE CRUZ (JAMACARU) | E6: 45691 | F6: 0 | G6: 0 | H6: 0
A7: F_Juazeiro | B7: Jefferson | C7: C03361 | D7: VICTOR HUGO DOS SANTOS ME | E7: 45691 | F7: 0 | G7: 0 | H7: 0
A8: F_Juazeiro | B8: Jefferson | C8: C04908 | D8: MERCADINHO SIEBRA | E8: 45691 | F8: 0 | G8: 0 | H8: 0
A9: F_Juazeiro | B9: Jefferson | C9: C05610 | D9: DROGAJACK | E9: 45691 | F9: 1 | G9: 0 | H9: 1
A10: F_Juazeiro | B10: Jefferson | C10: C08876 | D10: POSTO SANTO EXPEDITO | E10: 45691 | F10: 1 | G10: 0 | H10: 1
A11: F_Juazeiro | B11: Jefferson | C11: C08998 | D11: FARMACIA CLEIA | E11: 45691 | F11: 1 | G11: 0 | H11: 1
A12: F_Juazeiro | B12: Jefferson | C12: C09163 | D12: MERCANTIL GRANJEIRO | E12: 45691 | F12: 1 | G12: 0 | H12: 1
A13: F_Juazeiro | B13: Jefferson | C13: C11192 | D13: BOTECO DO RIQUIM | E13: 45691 | F13: 0 | G13: 0 | H13: 0
A14: F_Juazeiro | B14: Jefferson | C14: C11492 | D14: BREJO PARK | E14: 45691 | F14: 0 | G14: 0 | H14: 0
A15: F_Juazeiro | B15: Jefferson | C15: C11926 | D15: CHURRASCARIA CAICARA | E15: 45691 | F15: 1 | G15: 0 | H15: 1
A16: F_Juazeiro | B16: Jefferson | C16: C13387 | D16: BARATO ATACAREJO | E16: 45691 | F16: 0 | G16: 0 | H16: 0
... A2092: Telemarketing | B2092: Sujeiras TLM | C2092: C08325 | D2092: ADRIANA DA SILVA | E2092: 45691 | F2092: 0 | G2092: 0 | H2092: 0

Sheet 2 e 3 Meses_SC
A1: Supervisor | B1: Vendedor | C1: Cod_Cliente | D1: Nome_Fantasia | E1: Data_Cadastro | F1: Data_Ultima_Compra | G1: Status Equipamento | H1: Horizontal | I1: Vertical | J1: Total Equipamento | K1: Chamado | L1: Data_Abertura | M1: Data_Encerramento | N1: Status | O1: Tratativa | P1: Prazo | Q1: Responsável Direto | R1: Status2 | S1: Total Equipamento Atual
A2: F_Juazeiro | B2: Jefferson | C2: C05610 | D2: DROGAJACK | E2: 03/02/2025 | F2: 18/02/2026 | G2: 2 - Meses | H2: 1 | I2: 0 | J2: 1 | O2: SEM TRATATIVA | P2: 17/04/2026 | Q2: COMERCIAL | R2: PENDENTE | S2: 1
A3: F_Juazeiro | B3: Jefferson | C3: C08876 | D3: POSTO SANTO EXPEDITO | E3: 03/02/2025 | F3: 19/02/2026 | G3: 2 - Meses | H3: 1 | I3: 0 | J3: 1 | O3: POSITIVADO | P3: 17/04/2026 | Q3: COMERCIAL | R3: CONCLUIDO | S3: 1
A4: F_Juazeiro | B4: Morgana | C4: C22919 | D4: FARMACIAS GENTIL | E4: 03/02/2025 | F4: 26/01/2026 | G4: 3 - Meses | H4: 1 | I4: 0 | J4: 1 | O4: RECOLHIDO (NÃO POSSUI CHAMADO) | Q4: COMERCIAL | R4: PENDENTE | S4: 1
A5: F_Juazeiro | B5: Jefferson | C5: C09163 | D5: MERCANTIL GRANJEIRO | E5: 03/02/2025 | F5: 23/02/2026 | G5: 2 - Meses | H5: 1 | I5: 0 | J5: 1 | O5: POSITIVADO | P5: 17/04/2026 | Q5: COMERCIAL | R5: CONCLUIDO | S5: 1
A6: F_Juazeiro | B6: Jefferson | C6: C11926 | D6: CHURRASCARIA CAICARA | E6: 03/02/2025 | F6: 06/02/2026 | G6: 2 - Meses | H6: 1 | I6: 0 | J6: 1 | O6: POSITIVADO | P6: 17/04/2026 | Q6: COMERCIAL | R6: CONCLUIDO | S6: 1
A7: F_Juazeiro | B7: Jefferson | C7: C14885 | D7: BAR DE ELIANA | E7: 03/02/2025 | F7: 23/02/2026 | G7: 2 - Meses | H7: 1 | I7: 0 | J7: 1 | O7: SEM TRATATIVA | P7: 17/04/2026 | Q7: COMERCIAL | R7: PENDENTE | S7: 1
A8: F_Juazeiro | B8: Jefferson | C8: C15431 | D8: MERCADINHO DO MIGUEL | E8: 03/02/2025 | F8: 23/02/2026 | G8: 2 - Meses | H8: 1 | I8: 0 | J8: 1 | O8: POSITIVADO | P8: 17/04/2026 | Q8: COMERCIAL | R8: CONCLUIDO | S8: 1
A9: F_Juazeiro | B9: Jefferson | C9: C17751 | D9: CHACARA JM | E9: 03/02/2025 | F9: 20/02/2026 | G9: 2 - Meses | H9: 2 | I9: 0 | J9: 2 | O9: POSITIVADO | P9: 17/04/2026 | Q9: COMERCIAL | R9: CONCLUIDO | S9: 2
A10: F_Juazeiro | B10: Jefferson | C10: C18098 | D10: AGUAS FINAS BALNEARIO | E10: 03/02/2025 | F10: 12/02/2026 | G10: 2 - Meses | H10: 1 | I10: 0 | J10: 1 | O10: SEM TRATATIVA | P10: 17/04/2026 | Q10: COMERCIAL | R10: PENDENTE | S10: 1
A11: F_Juazeiro | B11: Jefferson | C11: C19137 | D11: MERCADINHO CLEOMARCIO ARMARINHO PM | E11: 03/02/2025 | F11: - | G11: 3 - Meses | H11: 1 | I11: 0 | J11: 1 | K11: ALTERAÇÃO CADASTRAL | L11: 14/04/2026 | M11: 46128 | N11: Encerrado | O11: ATUALIZAÇÃO CADASTRAL | P11: 46128 | Q11: MANUTENÇÃO | R11: CONCLUIDO | S11: 0
A12: F_Juazeiro | B12: Luan | C12: C24490 | D12: MARCONE SUPERMERCADO | E12: 03/02/2025 | F12: 04/04/2025 | G12: 3 - Meses | H12: 1 | I12: 0 | J12: 1 | O12: RECOLHIDO | Q12: MANUTENÇÃO | R12: PENDENTE | S12: 1
A13: F_Juazeiro | B13: Jefferson | C13: C25686 | D13: JULIA CRISTINA DE SA RORIZ MIRANDA | E13: 31/03/2025 | F13: 11/02/2026 | G13: 2 - Meses | H13: 1 | I13: 0 | J13: 1 | O13: POSITIVADO | P13: 17/04/2026 | Q13: COMERCIAL | R13: CONCLUIDO | S13: 1
A14: F_Juazeiro | B14: Jefferson | C14: C26788 | D14: WENDELL ALVES DA COSTA | E14: 01/07/2025 | F14: 13/04/2026 | G14: 2 - Meses | H14: 1 | I14: 0 | J14: 1 | O14: POSITIVADO | P14: 13/04/2026 | Q14: COMERCIAL | R14: CONCLUIDO | S14: 1
A15: F_Juazeiro | B15: Jefferson | C15: C28206 | D15: BALNEARIO RECANTO DO SOSSEGO | E15: 03/10/2025 | F15: 19/02/2026 | G15: 2 - Meses | H15: 1 | I15: 0 | J15: 1 | O15: POSITIVADO | P15: 17/04/2026 | Q15: COMERCIAL | R15: CONCLUIDO | S15: 1
A16: F_Juazeiro | B16: Luan | C16: C04806 | D16: JOSE SERGIO RODRIGUES CUNHA | E16: 03/02/2025 | F16: 24/02/2026 | G16: 2 - Meses | H16: 1 | I16: 0 | J16: 1 | O16: SEM TRATATIVA | P16: 17/04/2026 | Q16: COMERCIAL | R16: PENDENTE | S16: 1
A17: F_Juazeiro | B17: Luan | C17: C05139 | D17: REZORT LAZER DIVERSOES | E17: 03/02/2025 | F17: 10/02/2026 | G17: 2 - Meses | H17: 2 | I17: 0 | J17: 2 | O17: POSITIVADO | P17: 17/04/2026 | Q17: COMERCIAL | R17: CONCLUIDO | S17: 2
A18: F_Juazeiro | B18: Luan | C18: C05993 | D18: POUSADA MEDEIROS | E18: 03/02/2025 | F18: 19/12/2025 | G18: 3 - Meses | H18: 1 | I18: 0 | J18: 1 | O18: POSITIVADO | Q18: COMERCIAL | R18: CONCLUIDO | S18: 1
A19: F_Juazeiro | B19: Luan | C19: C10288 | D19: FARMACIA BOA ESPERANCA | E19: 03/02/2025 | F19: 30/01/2026 | G19: 2 - Meses | H19: 1 | I19: 0 | J19: 1 | O19: SEM TRATATIVA | P19: 17/04/2026 | Q19: COMERCIAL | R19: PENDENTE | S19: 1
A20: F_Juazeiro | B20: Luciano | C20: C19030 | D20: EMPORIO DAS AGUAS | E20: 03/02/2025 | F20: 30/01/2026 | G20: 3 - Meses | H20: 1 | I20: 0 | J20: 1 | K20: RECOLHA | L20: 14/04/2026 | M20: 15/04/2026 | N20: Encerrado | O20: EQUIPAMENTO RECOLHIDO | P20: 15/04/2026 | Q20: MANUTENÇÃO | R20: CONCLUIDO | S20: 0
A21: F_Juazeiro | B21: Luan | C21: C13405 | D21: TICO DA BODEGA | E21: 03/02/2025 | F21: 16/01/2026 | G21: 3 - Meses | H21: 1 | I21: 0 | J21: 1 | O21: VAI POSITIVAR | Q21: COMERCIAL | R21: PENDENTE | S21: 1
A22: F_Juazeiro | B22: Luan | C22: C14049 | D22: LANCHONETE MAIS DELICIA | E22: 03/02/2025 | F22: 13/04/2026 | G22: 2 - Meses | H22: 1 | I22: 0 | J22: 1 | O22: POSITIVADO | P22: 13/04/2026 | Q22: COMERCIAL | R22: CONCLUIDO | S22: 1
A23: F_Juazeiro | B23: Luan | C23: C14705 | D23: BAR DO LUCIANO | E23: 03/02/2025 | F23: 05/11/2025 | G23: 3 - Meses | H23: 1 | I23: 0 | J23: 1 | O23: VAI POSITIVAR | Q23: COMERCIAL | R23: PENDENTE | S23: 1
A24: F_Juazeiro | B24: Luan | C24: C15364 | D24: D M SUPERMERCADO | E24: 03/02/2025 | F24: 13/02/2026 | G24: 2 - Meses | H24: 1 | I24: 0 | J24: 1 | O24: SEM TRATATIVA | P24: 17/04/2026 | Q24: COMERCIAL | R24: PENDENTE | S24: 1
A25: F_Juazeiro | B25: Luan | C25: C20963 | D25: LANCHONETE PARADA OBRIGATORIA | E25: 31/01/2025 | F25: 27/02/2026 | G25: 2 - Meses | H25: 1 | I25: 0 | J25: 1 | O25: SEM TRATATIVA | P25: 17/04/2026 | Q25: COMERCIAL | R25: PENDENTE | S25: 1
A26: F_Juazeiro | B26: Luciano | C26: C25071 | D26: MERCADINHO PEIXOTO | E26: 03/02/2025 | F26: 29/01/2026 | G26: 3 - Meses | H26: 1 | I26: 0 | J26: 1 | O26: SEM TRATATIVA | Q26: COMERCIAL | R26: PENDENTE | S26: 1
A27: F_Juazeiro | B27: Luan | C27: C21220 | D27: ICE CREAM | E27: 03/02/2025 | F27: 09/04/2026 | G27: 3 - Meses | H27: 1 | I27: 0 | J27: 1 | O27: POSITIVADO | P27: 09/04/2026 | Q27: COMERCIAL | R27: CONCLUIDO | S27: 1
A28: F_Juazeiro | B28: Luan | C28: C22971 | D28: BAR DO NELDIM | E28: 03/02/2025 | F28: 16/04/2026 | G28: 2 - Meses | H28: 1 | I28: 0 | J28: 1 | O28: POSITIVADO | P28: 16/04/2026 | Q28: COMERCIAL | R28: CONCLUIDO | S28: 1
A29: F_Juazeiro | B29: Luan | C29: C23117 | D29: BAR DOS AMIGOS | E29: 03/02/2025 | F29: 20/01/2026 | G29: 3 - Meses | H29: 1 | I29: 0 | J29: 1 | O29: VAI POSITIVAR | Q29: COMERCIAL | R29: PENDENTE | S29: 1
A30: F_Juazeiro | B30: Luan | C30: C23789 | D30: BALNEARIO LUIZ FILHO | E30: 03/02/2025 | F30: 14/04/2026 | G30: 3 - Meses | H30: 1 | I30: 0 | J30: 1 | O30: POSITIVADO | P30: 14/04/2026 | Q30: COMERCIAL | R30: CONCLUIDO | S30: 1
A31: F_Juazeiro | B31: Luciano | C31: C26016 | D31: MERCEARIA DA JUCI | E31: 14/04/2025 | F31: 28/11/2025 | G31: 3 - Meses | H31: 1 | I31: 0 | J31: 1 | K31: RECOLHA | L31: 14/04/2026 | M31: 15/04/2026 | N31: Encerrado | O31: EQUIPAMENTO RECOLHIDO | P31: 15/04/2026 | Q31: MANUTENÇÃO | R31: CONCLUIDO | S31: 0
A32: F_Juazeiro | B32: Luan | C32: C24795 | D32: RENATO A DE SOUZA | E32: 03/02/2025 | F32: 15/04/2026 | G32: 2 - Meses | H32: 1 | I32: 0 | J32: 1 | O32: POSITIVADO | P32: 15/04/2026 | Q32: COMERCIAL | R32: CONCLUIDO | S32: 1
A33: F_Juazeiro | B33: Luan | C33: C24863 | D33: GELADAO DO CARNEIRINHO | E33: 03/02/2025 | F33: 15/04/2026 | G33: 3 - Meses | H33: 1 | I33: 0 | J33: 1 | O33: POSITIVADO | P33: 15/04/2026 | Q33: COMERCIAL | R33: CONCLUIDO | S33: 1
A34: F_Juazeiro | B34: Luan | C34: C28045 | D34: J CLEANTO SUPERMERCADO | E34: 22/09/2025 | F34: 26/02/2026 | G34: 2 - Meses | H34: 0 | I34: 1 | J34: 1 | O34: POSITIVADO | P34: 17/04/2026 | Q34: COMERCIAL | R34: CONCLUIDO | S34: 1
A35: F_Juazeiro | B35: Luan | C35: C28269 | D35: MOMENTOS GELADOS | E35: 09/10/2025 | F35: 14/04/2026 | G35: 2 - Meses | H35: 2 | I35: 0 | J35: 2 | O35: POSITIVADO | P35: 14/04/2026 | Q35: COMERCIAL | R35: CONCLUIDO | S35: 2
A36: F_Juazeiro | B36: Luciano | C36: C09335 | D36: POINT DO SORVETE | E36: 03/02/2025 | F36: 30/01/2026 | G36: 3 - Meses | H36: 1 | I36: 0 | J36: 1 | O36: VAI POSITIVAR | Q36: COMERCIAL | R36: PENDENTE | S36: 1
A37: F_Juazeiro | B37: Luciano | C37: C10158 | D37: POINT DO ACAI | E37: 03/02/2025 | F37: 21/02/2026 | G37: 2 - Meses | H37: 1 | I37: 0 | J37: 1 | O37: SEM TRATATIVA | P37: 17/04/2026 | Q37: COMERCIAL | R37: PENDENTE | S37: 1
A38: F_Juazeiro | B38: Luciano | C38: C10647 | D38: P & E VARIEDADES | E38: 03/02/2025 | F38: 23/02/2026 | G38: 2 - Meses | H38: 2 | I38: 0 | J38: 2 | O38: SEM TRATATIVA | P38: 17/04/2026 | Q38: COMERCIAL | R38: PENDENTE | S38: 2
A39: F_Juazeiro | B39: Jefferson | C39: C08998 | D39: FARMACIA CLEIA | E39: 03/02/2025 | F39: 14/11/2025 | G39: 3 - Meses | H39: 1 | I39: 0 | J39: 1 | K39: RECOLHA | L39: 13/04/2026 | N39: ABERTO | O39: RECOLHER | Q39: MANUTENÇÃO | R39: PENDENTE | S39: 1
A40: F_Juazeiro | B40: Luciano | C40: C19212 | D40: LIP PIZZAS E MASSAS | E40: 03/02/2025 | F40: 13/01/2026 | G40: 3 - Meses | H40: 1 | I40: 0 | J40: 1 | O40: VAI POSITIVAR | Q40: COMERCIAL | R40: PENDENTE | S40: 1
A41: F_Juazeiro | B41: Luciano | C41: C23476 | D41: NORMATEL HOME CENTER | E41: 03/02/2025 | F41: 31/12/2025 | G41: 3 - Meses | H41: 1 | I41: 0 | J41: 1 | O41: POSITIVADO | Q41: COMERCIAL | R41: CONCLUIDO | S41: 1
A42: F_Juazeiro | B42: Luciano | C42: C23844 | D42: ADEGA E TABACARIA HOUSE 24H | E42: 03/02/2025 | F42: 24/02/2026 | G42: 2 - Meses | H42: 1 | I42: 0 | J42: 1 | O42: POSITIVADO | P42: 17/04/2026 | Q42: COMERCIAL | R42: CONCLUIDO | S42: 1
A43: F_Juazeiro | B43: Luciano | C43: C24725 | D43: LEMOS BARBEARIA | E43: 03/02/2025 | F43: 25/02/2026 | G43: 2 - Meses | H43: 1 | I43: 0 | J43: 1 | O43: POSITIVADO | P43: 17/04/2026 | Q43: COMERCIAL | R43: CONCLUIDO | S43: 1
A44: F_Juazeiro | B44: Jefferson | C44: C24924 | D44: NAT SA SALGADOS | E44: 03/02/2025 | F44: 19/02/2025 | G44: 3 - Meses | H44: 1 | I44: 0 | J44: 1 | K44: RECOLHA | L44: 13/04/2026 | M44: 15/04/2026 | N44: Encerrado | O44: EQUIPAMENTO RECOLHIDO | P44: 15/04/2026 | Q44: MANUTENÇÃO | R44: CONCLUIDO | S44: 0
A45: F_Juazeiro | B45: Luan | C45: C10289 | D45: MERCADINHO BOA ESPERANCA | E45: 03/02/2025 | F45: 31/07/2025 | G45: 3 - Meses | H45: 1 | I45: 0 | J45: 1 | K45: RECOLHA | L45: 14/04/2026 | M45: 46132 | N45: Encerrado | O45: EQUIPAMENTO RECOLHIDO | P45: 46132 | Q45: MANUTENÇÃO | R45: CONCLUIDO | S45: 0
A46: F_Juazeiro | B46: Luciano | C46: C29843 | D46: L. P. MOREIRA LTDA | E46: 20/03/2026 | F46: - | G46: 3 - Meses | H46: 0 | I46: 1 | J46: 1 | O46: POSITIVADO | Q46: COMERCIAL | R46: CONCLUIDO | S46: 1
A47: F_Juazeiro | B47: Morgana | C47: C15815 | D47: FARMACIA GENTIL | E47: 03/02/2025 | F47: 19/01/2026 | G47: 3 - Meses | H47: 1 | I47: 0 | J47: 1 | O47: SEM TRATATIVA | Q47: COMERCIAL | R47: PENDENTE | S47: 1
A48: F_Juazeiro | B48: Luan | C48: C21000 | D48: LANCHONETE E PIZZARIA PAULISTA | E48: 03/02/2025 | F48: 18/11/2025 | G48: 3 - Meses | H48: 1 | I48: 0 | J48: 1 | K48: RECOLHA | L48: 15/04/2026 | M48: 46132 | N48: Encerrado | O48: EQUIPAMENTO RECOLHIDO | P48: 46132 | Q48: MANUTENÇÃO | R48: CONCLUIDO | S48: 0
A49: F_Juazeiro | B49: Morgana | C49: C24064 | D49: CARIRI CENTER SUPERMERCADOS (TRIANGULO) | E49: 03/02/2025 | F49: 04/02/2026 | G49: 2 - Meses | H49: 0 | I49: 1 | J49: 1 | O49: SEM TRATATIVA | P49: 17/04/2026 | Q49: COMERCIAL | R49: PENDENTE | S49: 1
A50: F_Maranhão | B50: Vinicius | C50: C18474 | D50: IRMAES GUIMARAES | E50: 03/02/2025 | F50: 13/04/2026 | G50: 2 - Meses | H50: 1 | I50: 0 | J50: 1 | O50: POSITIVADO | P50: 13/04/2026 | Q50: COMERCIAL | R50: CONCLUIDO | S50: 1
A51: F_Maranhão | B51: Vinicius | C51: C04035 | D51: ATACADAO (MARANHAO) | E51: 03/02/2025 | F51: 22/01/2026 | G51: 3 - Meses | H51: 0 | I51: 2 | J51: 2 | O51: SEM TRATATIVA | Q51: COMERCIAL | R51: PENDENTE | S51: 2
A52: F_Maranhão | B52: Vinicius | C52: C18012 | D52: BENJAS BURGUER | E52: 03/02/2025 | F52: 22/01/2026 | G52: 3 - Meses | H52: 1 | I52: 0 | J52: 1 | O52: NÃO POSSUI EQUIPAMENTO | Q52: MANUTENÇÃO | R52: PENDENTE | S52: 1
A53: F_Maranhão | B53: Vinicius | C53: C22647 | D53: VALEN SUPERMERCADO | E53: 03/02/2025 | F53: 16/07/2025 | G53: 3 - Meses | H53: 2 | I53: 0 | J53: 2 | O53: NÃO POSSUI EQUIPAMENTO | Q53: MANUTENÇÃO | R53: PENDENTE | S53: 2
A54: F_Maranhão | B54: Vinicius | C54: C26776 | D54: MERCADINHO SUCESSO | E54: 30/06/2025 | F54: - | G54: 3 - Meses | H54: 1 | I54: 0 | J54: 1 | O54: NÃO POSSUI EQUIPAMENTO | Q54: MANUTENÇÃO | R54: PENDENTE | S54: 1
A55: F_Mossoró | B55: Melo Monteiro | C55: C20701 | D55: SORVETERIA NESTOR | E55: 03/02/2025 | F55: 25/02/2026 | G55: 2 - Meses | H55: 1 | I55: 0 | J55: 1 | O55: CLIENTE NÃO QUER DEVOLVER O FREEZER - FREEZER COM PRODUTO | Q55: COMERCIAL | R55: PENDENTE | S55: 1
A56: F_Mossoró | B56: Melo Monteiro | C56: C24619 | D56: THE BRASA | E56: 03/02/2025 | F56: 19/02/2026 | G56: 2 - Meses | H56: 1 | I56: 0 | J56: 1 | O56: CLIENTE NÃO QUER MANUTENÇÃO, QUER TROCA | Q56: COMERCIAL | R56: PENDENTE | S56: 1
A57: F_Mossoró | B57: Melo Monteiro | C57: C26019 | D57: MERCEARIA DA ANA CARLA | E57: 14/04/2025 | F57: 24/02/2026 | G57: 2 - Meses | H57: 1 | I57: 0 | J57: 1 | O57: SEM TRATATIVA | Q57: COMERCIAL | R57: PENDENTE | S57: 1
A58: F_Mossoró | B58: Melo Monteiro | C58: C29438 | D58: SALT HAMBURGUERIA | E58: 30/01/2026 | F58: 10/02/2026 | G58: 2 - Meses | H58: 1 | I58: 0 | J58: 1 | O58: CLIENTE TEVE UMA TROCA DE EQUIPAMENTO DIA 31/03/2026 | Q58: COMERCIAL | R58: PENDENTE | S58: 1
A59: F_Mossoró | B59: Fábio | C59: C04683 | D59: HOTEL E CHURRASCARIA APODI | E59: 03/02/2025 | F59: - | G59: 3 - Meses | H59: 1 | I59: 0 | J59: 1 | O59: SEM TRATATIVA | Q59: COMERCIAL | R59: PENDENTE | S59: 1
A60: F_Mossoró | B60: Melo Monteiro | C60: C02970 | D60: REBOUCAS SUPERMERCADO SANTO ANTONIO | E60: 03/02/2025 | F60: 26/01/2026 | G60: 3 - Meses | H60: 3 | I60: 1 | J60: 4 | O60: SEM TRATATIVA | Q60: COMERCIAL | R60: PENDENTE | S60: 4
A61: F_Mossoró | B61: Melo Monteiro | C61: C02971 | D61: REBOUCAS SUPERMERCADO ALTO SAO MANOEL | E61: 31/01/2025 | F61: 26/01/2026 | G61: 3 - Meses | H61: 2 | I61: 0 | J61: 2 | O61: SEM TRATATIVA | Q61: COMERCIAL | R61: PENDENTE | S61: 2
A62: F_Mossoró | B62: Melo Monteiro | C62: C03024 | D62: REBOUCAS SUPERMERCADO (AÇU) | E62: 03/02/2025 | F62: 22/12/2025 | G62: 3 - Meses | H62: 1 | I62: 0 | J62: 1 | O62: NEGOCIANDO | Q62: COMERCIAL | R62: PENDENTE | S62: 1
... A67: F_Mossoró | B67: Melo Monteiro | C67: C17887 | D67: PANIFICADORA CEARA | E67: 03/02/2025 | F67: - | G67: 3 - Meses | H67: 1 | I67: 0 | J67: 1 | O67: SEM TRATATIVA | Q67: COMERCIAL | R67: PENDENTE | S67: 1
A68: F_Mossoró | B68: Melo Monteiro | C68: C25972 | D68: SELETO GASTROBAR E POUSADA | E68: 10/04/2025 | F68: 04/11/2025 | G68: 3 - Meses | H68: 1 | I68: 0 | J68: 1 | K68: RECOLHA | L68: 46126 | M68: 46139 | N68: Encerrado | O68: EQUIPAMENTO RECOLHIDO | P68: 46139 | Q68: MANUTENÇÃO | R68: CONCLUIDO | S68: 0
A69: F_Mossoró | B69: Melo Monteiro | C69: C27685 | D69: VILA CAICARA | E69: 26/08/2025 | F69: 01/10/2025 | G69: 3 - Meses | H69: 1 | I69: 0 | J69: 1 | K69: RECOLHA | L69: 14/04/2026 | M69: 46139 | N69: Encerrado | O69: EQUIPAMENTO RECOLHIDO | P69: 46139 | Q69: MANUTENÇÃO | R69: CONCLUIDO | S69: 0
A70: F_Mossoró | B70: Melo Monteiro | C70: C27994 | D70: RESTO CHACAL DANTAS | E70: 17/09/2025 | F70: 03/10/2025 | G70: 3 - Meses | H70: 1 | I70: 0 | J70: 1 | K70: RECOLHA | L70: 15/04/2026 | N70: ABERTO | O70: RECOLHER | Q70: MANUTENÇÃO | R70: PENDENTE | S70: 1
A71: F_Pernambuco_VA | B71: Airmes | C71: C11105 | D71: ATACADAO SERRA TALHADA | E71: 03/02/2025 | F71: 28/03/2026 | G71: 2 - Meses | H71: 0 | I71: 1 | J71: 1 | O71: SEM TRATATIVA | Q71: COMERCIAL | R71: PENDENTE | S71: 1
A72: F_Pernambuco_VA | B72: Emanoel | C72: C23738 | D72: WELLINGTON GOMES DE SIQUEIRA | E72: 03/02/2025 | F72: 20/02/2026 | G72: 2 - Meses | H72: 1 | I72: 0 | J72: 1 | O72: SEM TRATATIVA | Q72: COMERCIAL | R72: PENDENTE | S72: 1
A73: F_Pernambuco_VA | B73: Geraldo | C73: C21932 | D73: FORTE ACAI | E73: 03/02/2025 | F73: 18/02/2026 | G73: 2 - Meses | H73: 1 | I73: 0 | J73: 1 | O73: SEM TRATATIVA | Q73: COMERCIAL | R73: PENDENTE | S73: 1
A74: F_Pernambuco_AS | B74: Nacionais PE | C74: C28947 | D74: MIX MATEUS (DISTRITO INDUSTRIAL - PETROLINA) | E74: 03/12/2025 | F74: 08/01/2026 | G74: 3 - Meses | H74: 0 | I74: 1 | J74: 1 | O74: CLIENTE TEM 1 PEDIDO PENDENTE QUE DA UM VALOR DE 2.290,12 (JAN) | Q74: COMERCIAL | R74: PENDENTE | S74: 1
A75: F_Pernambuco_PB | B75: Ladjane de Oliveira | C75: C26469 | D75: SUPERMERCADO MATEUS (VALENTINA DE FIGUEIREDO) | E75: 31/05/2025 | F75: 22/01/2026 | G75: 3 - Meses | H75: 0 | I75: 1 | J75: 1 | O75: SEM TRATATIVA | Q75: COMERCIAL | R75: PENDENTE | S75: 1
A76: F_Pernambuco_PB | B76: Ladjane de Oliveira | C76: C26473 | D76: SUPERMERCADO MATEUS (CAJAZEIRAS) | E76: 31/05/2025 | F76: 17/11/2025 | G76: 3 - Meses | H76: 0 | I76: 1 | J76: 1 | O76: SEM TRATATIVA | Q76: COMERCIAL | R76: PENDENTE | S76: 1
A77: F_Pernambuco_PB | B77: Ladjane de Oliveira | C77: C26474 | D77: SUPERMERCADO MATEUS (CAMPINA GRANDE) | E77: 01/06/2025 | F77: 17/11/2025 | G77: 3 - Meses | H77: 0 | I77: 1 | J77: 1 | O77: SEM TRATATIVA | Q77: COMERCIAL | R77: PENDENTE | S77: 1
A78: F_Pernambuco_PB | B78: Ladjane de Oliveira | C78: C26476 | D78: SUPERMERCADO MATEUS (BAYEUX) | E78: 01/06/2025 | F78: 18/12/2025 | G78: 3 - Meses | H78: 0 | I78: 1 | J78: 1 | O78: SEM TRATATIVA | Q78: COMERCIAL | R78: PENDENTE | S78: 1
A79: F_Pernambuco_PB | B79: Ladjane de Oliveira | C79: C26477 | D79: SUPERMERCADO MATEUS (CABEDELO) | E79: 01/06/2025 | F79: 18/12/2025 | G79: 3 - Meses | H79: 0 | I79: 1 | J79: 1 | O79: SEM TRATATIVA | Q79: COMERCIAL | R79: PENDENTE | S79: 1
A80: F_Pernambuco_VA | B80: André Luiz | C80: C23316 | D80: AQUI FARMA | E80: 03/02/2025 | F80: 24/09/2025 | G80: 3 - Meses | H80: 1 | I80: 0 | J80: 1 | O80: SEM TRATATIVA | Q80: COMERCIAL | R80: PENDENTE | S80: 1
A81: F_Pernambuco_VA | B81: Aprigio | C81: C25689 | D81: CANTO DO TEMPERO | E81: 31/03/2025 | F81: 15/08/2025 | G81: 3 - Meses | H81: 1 | I81: 0 | J81: 1 | O81: SEM TRATATIVA | Q81: COMERCIAL | R81: PENDENTE | S81: 1
A82: F_Pernambuco_VA | B82: Emanoel | C82: C26436 | D82: MERCEARIA JARDIM PIEDADE | E82: 28/05/2025 | F82: 24/10/2025 | G82: 3 - Meses | H82: 1 | I82: 0 | J82: 1 | O82: SEM TRATATIVA | Q82: COMERCIAL | R82: PENDENTE | S82: 1
... A88: F_Pernambuco_VA | B88: Leucio Pereira | C88: C26038 | D88: CHICAO MERCEARIA | E88: 15/04/2025 | F88: 21/07/2026 | G88: 3 - Meses | H88: 0 | I88: 1 | J88: 1 | O88: SEM TRATATIVA | Q88: COMERCIAL | R88: PENDENTE | S88: 1
A89: F_Sobral | B89: Adriano | C89: C01043 | D89: BALNEARIO ELIENEIDE | E89: 31/01/2025 | F89: 20/02/2026 | G89: 2 - Meses | H89: 1 | I89: 0 | J89: 1 | K89: ALTERAÇÃO CADASTRAL | L89: 46129 | M89: 46129 | N89: Encerrado | O89: ALTERAÇÃO CADASTRAL - COD_NOVO: C29717 | P89: 15/04/2026 | Q89: MANUTENÇÃO | R89: CONCLUIDO | S89: 0
A90: F_Sobral | B90: Adriano | C90: C29584 | D90: O BOM DA TERRA | E90: 23/02/2026 | F90: 20/03/2026 | G90: 2 - Meses | H90: 1 | I90: 0 | J90: 1 | O90: POSITIVADO | P90: 30/04/2026 | Q90: COMERCIAL | R90: CONCLUIDO | S90: 1
A91: F_Sobral | B91: Adriano | C91: C01188 | D91: IVANILDA AZEVEDO BARBOSA | E91: 31/01/2025 | F91: 12/01/2026 | G91: 3 - Meses | H91: 1 | I91: 0 | J91: 1 | O91: ALINHAR RECOLHA | P91: 20/04/2026 | Q91: COMERCIAL | R91: PENDENTE | S91: 1
A92: F_Sobral | B92: Adriano | C92: C06559 | D92: PARATY SUPERMERCADO (ITAPAGE) | E92: 03/02/2025 | F92: 11/10/2026 | G92: 3 - Meses | H92: 0 | I92: 1 | J92: 1 | O92: LOJA FECHOU - ALINHAR COM O DONO A RECOLHA | P92: 20/04/2026 | Q92: COMERCIAL | R92: PENDENTE | S92: 1
A93: F_Sobral | B93: Adriano | C93: C14883 | D93: CHURRASCARIA O KAKI | E93: 03/02/2025 | F93: 29/01/2026 | G93: 3 - Meses | H93: 1 | I93: 0 | J93: 1 | K93: ALTERAÇÃO CADASTRAL | L93: 46129 | M93: 46129 | N93: Encerrado | O93: ALTERAÇÃO CADASTRAL - COD_NOVO: C29718 | P93: 15/04/2026 | Q93: MANUTENÇÃO | R93: CONCLUIDO | S93: 0
A94: F_Sobral | B94: Adriano | C94: C16196 | D94: HJ CONSTRUCAO E MERCEARIA | E94: 03/02/2025 | F94: 15/01/2026 | G94: 3 - Meses | H94: 1 | I94: 0 | J94: 1 | O94: EQUIPAMENTO COM PRODUTO | Q94: COMERCIAL | R94: PENDENTE | S94: 1
A95: F_Sobral | B95: Adriano | C95: C19359 | D95: PARATY SUPERMERCADO LTDA (URUBURETAMA) | E95: 03/02/2025 | F95: 11/10/2025 | G95: 3 - Meses | H95: 0 | I95: 1 | J95: 1 | K95: RECOLHA | L95: 46135 | M95: 46135 | N95: Encerrado | O95: LOJA FECHOU - ALINHAR COM O DONO A RECOLHA | P95: 20/04/2026 | Q95: MANUTENÇÃO | R95: CONCLUIDO | S95: 0
A96: F_Sobral | B96: Aglailson | C96: C00855 | D96: MERCADINHO LOIOLA (SANTA QUITERIA) | E96: 31/01/2025 | F96: 03/02/2026 | G96: 2 - Meses | H96: 1 | I96: 0 | J96: 1 | O96: POSITIVADO | P96: 15/04/2026 | Q96: COMERCIAL | R96: CONCLUIDO | S96: 1
A97: F_Sobral | B97: Aglailson | C97: C00857 | D97: COM JOSE MARIA (SANTA QUITERIA) | E97: 31/01/2025 | F97: 15/04/2026 | G97: 2 - Meses | H97: 2 | I97: 0 | J97: 2 | O97: POSITIVADO | P97: 17/04/2026 | Q97: COMERCIAL | R97: CONCLUIDO | S97: 2
A98: F_Sobral | B98: Aglailson | C98: C11238 | D98: ESTACAO LANCHE | E98: 03/02/2025 | F98: 06/02/2026 | G98: 2 - Meses | H98: 1 | I98: 0 | J98: 1 | O98: POSITIVADO | P98: 17/04/2026 | Q98: COMERCIAL | R98: CONCLUIDO | S98: 1
A99: F_Sobral | B99: Aglailson | C99: C28078 | D99: GUDYS GRILL | E99: 24/09/2025 | F99: 26/02/2026 | G99: 2 - Meses | H99: 1 | I99: 0 | J99: 1 | O99: VAI POSITIVAR | P99: 17/04/2026 | Q99: COMERCIAL | R99: PENDENTE | S99: 1
A100: F_Sobral | B100: Aglailson | C100: C04946 | D100: MERCANTIL AGUIAR | E100: 03/02/2025 | F100: 04/04/2026 | G100: 3 - Meses | H100: 2 | I100: 0 | J100: 2 | O100: POSITIVOU | P100: 04/04/2026 | Q100: COMERCIAL | R100: CONCLUIDO | S100: 2
A101: F_Sobral | B101: Aglailson | C101: C08675 | D101: MERCADINHO JB | E101: 03/02/2025 | F101: 16/04/2026 | G101: 3 - Meses | H101: 1 | I101: 0 | J101: 1 | O101: POSITIVADO | P101: 17/04/2026 | Q101: COMERCIAL | R101: CONCLUIDO | S101: 1
A102: F_Sobral | B102: Aglailson | C102: C15271 | D102: DUETO BAR | E102: 03/02/2025 | F102: 25/09/2025 | G102: 3 - Meses | H102: 1 | I102: 0 | J102: 1 | K102: RECOLHA | L102: 46129 | M102: 46135 | N102: Encerrado | O102: EQUIPAMENTO RECOLHIDO | P102: 46135 | Q102: MANUTENÇÃO | R102: CONCLUIDO | S102: 0
A103: F_Sobral | B103: Aglailson | C103: C16193 | D103: BEIRA RIO PARK | E103: 03/02/2025 | F103: 28/11/2025 | G103: 3 - Meses | H103: 2 | I103: 0 | J103: 2 | O103: VAI POSITIVAR | P103: 17/04/2026 | Q103: COMERCIAL | R103: PENDENTE | S103: 2
A104: F_Sobral | B104: Aglailson | C104: C23232 | D104: VIA CANINDE | E104: 03/02/2025 | F104: 28/10/2025 | G104: 3 - Meses | H104: 1 | I104: 0 | J104: 1 | K104: RECOLHA | L104: 46129 | M104: 46135 | N104: Encerrado | O104: EQUIPAMENTO RECOLHIDO | P104: 46135 | Q104: MANUTENÇÃO | R104: CONCLUIDO | S104: 0
A105: F_Sobral | B105: Aglailson | C105: C23568 | D105: ATACAREJO MONTES | E105: 03/02/2025 | F105: 16/01/2026 | G105: 3 - Meses | H105: 1 | I105: 0 | J105: 1 | O105: VAI POSITIVAR | P105: 17/04/2026 | Q105: COMERCIAL | R105: PENDENTE | S105: 1
A106: F_Sobral | B106: Aglailson | C106: C24654 | D106: MERCADINHO OLIVEIRA | E106: 03/02/2025 | F106: 28/02/2026 | G106: 3 - Meses | H106: 1 | I106: 0 | J106: 1 | O106: VAI POSITIVAR | P106: 17/04/2026 | Q106: COMERCIAL | R106: PENDENTE | S106: 1
A107: F_Sobral | B107: Aglailson | C107: C25023 | D107: AÇAITERIA 2 AMORES | E107: 03/02/2025 | F107: 18/09/2025 | G107: 3 - Meses | H107: 1 | I107: 0 | J107: 1 | O107: ABRIR CHAMADO DE RECOLHA | Q107: BACKOFFICE | R107: PENDENTE | S107: 1
A108: F_Sobral | B108: Aglailson | C108: C28354 | D108: FABIO DISTRIBUIDORA | E108: 15/10/2025 | F108: 28/01/2026 | G108: 3 - Meses | H108: 1 | I108: 0 | J108: 1 | O108: VAI POSITIVAR | P108: 17/04/2026 | Q108: COMERCIAL | R108: PENDENTE | S108: 1
A109: F_Sobral | B109: Antonio Pereira | C109: C19049 | D109: MERCADO E PANIFICADORA GUAPORE | E109: 03/02/2025 | F109: 24/02/2026 | G109: 2 - Meses | H109: 1 | I109: 0 | J109: 1 | O109: POSITIVADO | P109: 20/04/2026 | Q109: COMERCIAL | R109: CONCLUIDO | S109: 1
...

Sheet dCliente
A1: supervisor | B1: cod_supervisor | C1: vendedor | D1: cod_vendedor | E1: promotor | F1: cod_promotor | G1: rede | H1: cod_cliente | I1: nome_fantasia | J1: razao_social | K1: cod_segmento | L1: segmento | M1: cod_canal | N1: canal | O1: tipo_cadastro | P1: ativo | Q1: bairro | R1: cidade | S1: estado | T1: pais | U1: data_cadastro | V1: data_inativacao | W1: cnpj | X1: dia_roteiro | Y1: periodo_visita | Z1: desc.pontual | AA1: utilizacao | AB1: prazo_pagamento | AC1: Banco | AD1: lista_preco | AE1: cep | AF1: latitude | AG1: longitude | AH1: bloqueio_inadimplente | AI1: spc | AJ1: credito_limitado | AK1: saldo_conta | AL1: limite_credito | AM1: Horizontal | AN1: Vertical | AO1: Total Equipamento | AP1: Venda_MesAnt3 | AQ1: Venda_MesAnt2 | AR1: Venda_MesAnt | AS1: Venda_MesAtual | AT1: Positivado_MesAnt3 > 300 | AU1: Positivado_MesAnt2 > 300 | AV1: Positivado_MesAnt > 300 | AW1: Positivado_MesAtual > 300 | AX1: MetaPositivaçãoMesAnt3 | AY1: MetaPositivaçãoMesAnt2 | AZ1: MetaPositivaçãoMesAnt | BA1: MetaPositivaçãoMesAtual | BB1: MetaGiro_MesAnt3 | BC1: MetaGiro_MesAnt2 | BD1: MetaGiro_MesAnt | BE1: MetaGiro_MesAtual | BF1: RealGiro_MesAnt3 | BG1: RealGiro_MesAnt2 | BH1: RealGiro_MesAnt | BI1: RealGiro_MesAtual | BJ1: Giro_MesAnt3 | BK1: Giro_MesAnt2 | BL1: Giro_MesAnt | BM1: Giro_MesAtual | BN1: Real_Giro_MesAnt3 | BO1: Real_Giro_MesAnt2 | BP1: Real_Giro_MesAnt | BQ1: Real_Giro_MesAtual | BR1: Atg_Giro_MesAnt3 | BS1: Atg_Giro_MesAnt2 | BT1: Atg_Giro_MesAnt | BU1: Atg_Giro_MesAtual | BV1: Ticket Médio 3M | BW1: Sem_compra_vertical_MesAnt3 | BX1: Sem_compra_vertacal_MesAnt2 | BY1: Sem_compra_vertical_MesAnt | BZ1: Sem_compra_vertical_MesAtual | CA1: Gerência | CB1: Canal_RCA | CC1: Canal_Id | CD1: latitude_Cliente | CE1: longitude_cliente | CF1: Meses S/ Compra | CG1: Status Equipamento | CH1: ClassificaçãoId | CI1: ClassificaçãoName
A2: M_Capital | B2: 1441 | C2: Alexsanderson | D2: 1061 | G2: CLIENTES | H2: C00010 | I2: FARMACIA OPCAO | J2: FARMACIA OPCAO LTDA | K2: 11 | M2: 7 | N2: PEQUENO VAREJO | O2: C | P2: Y | Q2: Dionisio Torres | R2: Fortaleza | S2: CE | T2: BR | U2: 45688 | X2: Ter | Y2: Q2 | AA2: Revenda | AB2: 7 dias | AC2: BLT-ITAÚ 130681 | AD2: CAPITAL CE | AE2: 60135-102 | AF2: -3.745251 | AG2: -38.5035444 | AH2: Sim | AI2: Não | AJ2: Sim | AK2: 1973.96 | AL2: 1100 | AM2: 0 | AN2: 0 | AO2: 0 | AP2: 0 | AQ2: 0 | AR2: 0 | AS2: 0 | AT2: 0 | AU2: 0 | AV2: 0 | AW2: 0 | AX2: 1 | AY2: 1 | AZ2: 1 | BA2: 1 | BV2: 0 | BW2: 0 | BX2: 0 | BY2: 0 | BZ2: 0 | CA2: CE | CB2: Varejo | CC2: Vendedor/Varejo | CD2: -3745251 | CE2: -38503544 | CF2: 3 | CG2: 3 - Meses | CH2: 0 - S/COMPRA | CI2: 0 - <= 0
A3: M_Capital | B3: 1441 | C3: Alexsanderson | D3: 1061 | G3: CLIENTES | H3: C00043 | I3: SWEET MIMOS (LEIRIE DE ANDRADE) | J3: SWEET MIMOS COM DE UTILIDADES LTDA | K3: 24 | M3: 7 | N3: PEQUENO VAREJO | O3: C | P3: Y | Q3: JOAQUIM TAVORA | R3: FORTALEZA | S3: CE | T3: BR | U3: 45688 | X3: Ter | Y3: Q2 | AA3: Revenda | AB3: 15 dias | AC3: BLT-SOF | AD3: CAPITAL CE | AE3: 60115-001 | AF3: -3.7388948 | AG3: -38.5150676 | AH3: Sim | AI3: Não | AJ3: Não | AK3: 0 | AL3: 800 | AM3: 0 | AN3: 0 | AO3: 0 | AP3: 0 | AQ3: 0 | AR3: 0 | AS3: 0 | AT3: 0 | AU3: 0 | AV3: 0 | AW3: 0 | AX3: 1 | AY3: 1 | AZ3: 1 | BA3: 1 | BV3: 0 | BW3: 0 | BX3: 0 | BY3: 0 | BZ3: 0 | CA3: CE | CB3: Varejo | CC3: Vendedor/Varejo | CD3: -37388948 | CE3: -38515067 | CF3: 3 | CG3: 3 - Meses | CH3: 0 - S/COMPRA | CI3: 0 - <= 0
A4: M_Nacionais | B4: 12 | C4: Lettelie | D4: 996 | G4: NOVA REDE | H4: C00074 | I4: MERCADINHO ARCO VERDE | J4: JOAO BATISTA DA S GEN ALIM LTDA | K4: 1 | M4: 1 | N4: AUTOSSERVIÇO REGIONAL | O4: C | P4: Y | Q4: Jardim Petropolis | R4: Fortaleza | S4: CE | T4: BR | U4: 45688 | X4: Qua | Y4: Semanal | AA4: Revenda | AB4: 15 dias | AC4: BLT-ITAÚ 130681 | AD4: AUTOSSERVIÇO CE | AE4: 60332-100 | AF4: -3.7027092 | AG4: -38.57606 | AH4: Sim | AI4: Não | AJ4: Não | AK4: 0 | AL4: 1350 | AM4: 0 | AN4: 0 | AO4: 0 | AP4: 0 | AQ4: 0 | AR4: 0 | AS4: 0 | AT4: 0 | AU4: 0 | AV4: 0 | AW4: 0 | AX4: 1 | AY4: 1 | AZ4: 1 | BA4: 1 | BV4: 0 | BW4: 0 | BX4: 0 | BY4: 0 | BZ4: 0 | CA4: CE | CB4: AS | CC4: Vendedor/AS | CD4: -37027092 | CE4: -3857606 | CF4: 3 | CG4: 3 - Meses | CH4: 0 - S/COMPRA | CI4: 0 - <= 0
A5: Marujinho | B5: 143 | C5: Jacilane | D5: 1040 | G5: DISTRI CAPITAL MARUJ | H5: C00133 | I5: ELENITA GOMES | J5: ELENITA GOMES DA COSTA | K5: 9 | M5: 6 | N5: DISTRIBUIDORES | O5: C | P5: Y | Q5: ITAMBE II | R5: CAUCAIA | S5: CE | T5: BR | U5: 45688 | X5: Qui | Y5: Semanal | AA5: Revenda | AB5: a vista | AC5: BLT-SANT 804-1 | AD5: MARUJINHO DIST CAPITAL DUPLICATA | AE5: 61602-650 | AF5: -3.728651 | AG5: -38.646193 | AH5: Sim | AI5: Não | AJ5: Sim | AK5: 3723.69 | AL5: 0 | AM5: 2 | AN5: 0 | AO5: 2 | AP5: 0 | AQ5: 436.36 | AR5: 0 | AS5: 0 | AT5: 0 | AU5: 1 | AV5: 0 | AW5: 0 | AX5: 1 | AY5: 1 | AZ5: 1 | BA5: 1 | BB5: 1200 | BC5: 1200 | BD5: 1200 | BE5: 1200 | BF5: 0 | BG5: 0.36363333 | BH5: 0 | BI5: 0 | BJ5: 2 | BK5: 2 | BL5: 2 | BM5: 2 | BN5: 0 | BO5: 0 | BP5: 0 | BQ5: 0 | BR5: 0 | BS5: 0 | BT5: 0 | BU5: 0 | BV5: 145.45333 | BW5: 0 | BX5: 0 | BY5: 0 | BZ5: 0 | CA5: TELEVENDAS | CB5: Marujinho | CC5: Vendedor/Marujinho | CD5: -3728651 | CE5: -38646193 | CF5: 2 | CG5: 2 - Meses | CH5: 1 - PÉSSIMO | CI5: 1 - < 300
A6: M_Capital | B6: 1441 | C6: Francineudo | D6: 1013 | G6: CLIENTES | H6: C00143 | I6: MERCADINHO PAULO E RISALVA | J6: PAULO SERGIO DE ALMEIDA ME | K6: 15 | M6: 7 | N6: PEQUENO VAREJO | O6: C | P6: Y | Q6: Horizonte | R6: Horizonte | S6: CE | T6: BR | U6: 45688 | X6: Sex | Y6: Semanal | AA6: Revenda | AB6: 21 dias | AC6: BLT-SOF | AD6: INTERIOR CE | AE6: 62880-000 | AF6: -4.0975048 | AG6: -38.4913877 | AH6: Sim | AI6: Não | AJ6: Não | AK6: 950.15 | AL6: 1000 | AM6: 0 | AN6: 0 | AO6: 0 | AP6: 0 | AQ6: 0 | AR6: 0 | AS6: 0 | AT6: 0 | AU6: 0 | AV6: 0 | AW6: 0 | AX6: 1 | AY6: 1 | AZ6: 1 | BA6: 1 | BV6: 0 | BW6: 0 | BX6: 0 | BY6: 0 | BZ6: 0 | CA6: CE | CB6: Varejo | CC6: Vendedor/Varejo | CD6: -40975048 | CE6: -38491387 | CF6: 3 | CG6: 3 - Meses | CH6: 0 - S/COMPRA | CI6: 0 - <= 0
A7: F_Sobral | B7: 2465 | C7: Bruno | D7: 1004 | G7: CLIENTES | H7: C00262 | I7: DISTAK LANCHES | J7: JOSE OSMAR DE OLIVEIRA | K7: 24 | M7: 7 | N7: PEQUENO VAREJO | O7: C | P7: Y | Q7: ACARAU | R7: ACARAÚ | S7: CE | T7: BR | U7: 45688 | X7: Seg | Y7: Q1 | AA7: Revenda | AB7: 13 dias | AC7: BLT-SOF | AD7: CAPITAL CE | AE7: 62580-000 | AF7: -2.885395 | AG7: -40.117661 | AH7: Sim | AI7: Não | AJ7: Não | AK7: 0 | AL7: 500 | AM7: 1 | AN7: 0 | AO7: 1 | AP7: 436.8 | AQ7: 607.32 | AR7: 0 | AS7: 0 | AT7: 1 | AU7: 1 | AV7: 0 | AW7: 0 | AX7: 1 | AY7: 1 | AZ7: 1 | BA7: 1 | BB7: 600 | BC7: 600 | BD7: 600 | BE7: 600 | BF7: 0.728 | BG7: 1.0122 | BH7: 0 | BI7: 0 | BJ7: 1 | BK7: 1 | BL7: 1 | BM7: 1 | BN7: 0 | BO7: 1 | BP7: 0 | BQ7: 0 | BR7: 0 | BS7: 1 | BT7: 0 | BU7: 0 | BV7: 348.04 | BW7: 0 | BX7: 0 | BY7: 0 | BZ7: 0 | CA7: CE | CB7: Varejo | CC7: Vendedor/Varejo | CD7: -2885395 | CE7: -40117661 | CF7: 2 | CG7: 2 - Meses | CH7: 2 - RUIM | CI7: 2 - < 600
A8: F_Sobral | B8: 2465 | C8: Adriano | D8: 993 | G8: CLIENTES | H8: C00264 | I8: L D I LANCHES | J8: FRANCISCO DARIO CAVALCANTE ME | K8: 24 | M8: 7 | N8: PEQUENO VAREJO | O8: C | P8: Y | Q8: CENTRO | R8: ITAPIPOCA | S8: CE | T8: BR | U8: 45688 | X8: Ter | Y8: Q1 | AA8: Revenda | AB8: 13 dias | AC8: BLT-SOF | AD8: VAREJO - SOBRAL | AE8: 62500-061 | AF8: -3.5009615 | AG8: -39.5836111 | AH8: Sim | AI8: Não | AJ8: Não | AK8: 0 | AL8: 500 | AM8: 0 | AN8: 0 | AO8: 0 | AP8: 0 | AQ8: 304.59 | AR8: 0 | AS8: 0 | AT8: 0 | AU8: 1 | AV8: 0 | AW8: 0 | AX8: 1 | AY8: 1 | AZ8: 1 | BA8: 1 | BV8: 101.53 | BW8: 0 | BX8: 0 | BY8: 0 | BZ8: 0 | CA8: CE | CB8: Varejo | CC8: Vendedor/Varejo | CD8: -35009615 | CE8: -39583611 | CF8: 2 | CG8: 2 - Meses | CH8: 1 - PÉSSIMO | CI8: 1 - < 300
A9: F_Sobral | B9: 2465 | C9: Gonzarlen | D9: 995 | G9: CLIENTES | H9: C00346 | I9: POSTO NORONHA (BR 020) | J9: NORONHA DIST DE PETROLEO LTDA | K9: 13 | M9: 7 | N9: PEQUENO VAREJO | O9: C | P9: Y | Q9: Campos Belos | R9: Caridade | S9: CE | T9: BR | U9: 45688 | X9: Seg | Y9: Q2 | AA9: Revenda | AB9: 21 dias | AC9: BLT-SANT 804-1 | AD9: INTERIOR CE | AE9: 62730-000 | AF9: -4.3692851 | AG9: -39.3206587 | AH9: Sim | AI9: Não | AJ9: Não | AK9: 0 | AL9: 1604 | AM9: 2 | AN9: 0 | AO9: 2 | AP9: 637 | AQ9: 0 | AR9: 0 | AS9: 0 | AT9: 1 | AU9: 0 | AV9: 0 | AW9: 0 | AX9: 1 | AY9: 1 | AZ9: 1 | BA9: 1 | BB9: 1200 | BC9: 1200 | BD9: 1200 | BE9: 1200 | BF9: 0.53083333 | BG9: 0 | BH9: 0 | BI9: 0 | BJ9: 2 | BK9: 2 | BL9: 2 | BM9: 2 | BN9: 0 | BO9: 0 | BP9: 0 | BQ9: 0 | BR9: 0 | BS9: 0 | BT9: 0 | BU9: 0 | BV9: 212.33333 | BW9: 0 | BX9: 0 | BY9: 0 | BZ9: 0 | CA9: CE | CB9: Varejo | CC9: Vendedor/Varejo | CD9: -43692851 | CE9: -39320658 | CF9: 3 | CG9: 3 - Meses | CH9: 1 - PÉSSIMO | CI9: 1 - < 300
A10: M_Nacionais | B10: 12 | C10: Lettelie | D10: 996 | G10: CLIENTES | H10: C00375 | I10: SUPER PONTO DA ECONOMIA | J10: PONTO DA ECONOMIA COMERCIAL DE ALIMENTOS LTDA - ME | K10: 1 | M10: 1 | N10: AUTOSSERVIÇO REGIONAL | O10: C | P10: Y | Q10: AEROLANDIA | R10: FORTALEZA | S10: CE | T10: BR | U10: 45691 | X10: Seg | Y10: Semanal | AA10: Revenda | AB10: 21 dias | AC10: BLT-SOF | AD10: AUTOSSERVIÇO CE | AE10: 60851-290 | AF10: -3.777306 | AG10: -38.513074 | AH10: Sim | AI10: Não | AJ10: Não | AK10: 0 | AL10: 1500 | AM10: 0 | AN10: 0 | AO10: 0 | AP10: 0 | AQ10: 0 | AR10: 0 | AS10: 0 | AT10: 0 | AU10: 0 | AV10: 0 | AW10: 0 | AX10: 1 | AY10: 1 | AZ10: 1 | BA10: 1 | BV10: 0 | BW10: 0 | BX10: 0 | BY10: 0 | BZ10: 0 | CA10: CE | CB10: AS | CC10: Vendedor/AS | CD10: -3777306 | CE10: -38513074 | CF10: 3 | CG10: 3 - Meses | CH10: 0 - S/COMPRA | CI10: 0 - <= 0
A11: M_Capital | B11: 1441 | C11: Leonardo | D11: 1007 | G11: CLIENTES | H11: C00423 | I11: CHURRASCARIA FERNANDES | J11: ALDENIRA DUARTE DE OLIVEIRA | K11: 31 | M11: 10 | N11: INATIVO | O11: C | P11: Y | Q11: BARRA DO CEARA | R11: FORTALEZA | S11: CE | T11: BR | U11: 45691 | X11: Qui | Y11: Semanal | AA11: Revenda | AB11: 5 dias | AC11: DINHEIRO$ | AD11: LOJA - CEARÁ - ATACADO | AE11: 60332-360 | AF11: -3.700796 | AG11: -38.578752 | AH11: Sim | AI11: Não | AJ11: Não | AK11: 0 | AL11: 0 | AM11: 0 | AN11: 0 | AO11: 0 | AP11: 0 | AQ11: 0 | AR11: 0 | AS11: 0 | AT11: 0 | AU11: 0 | AV11: 0 | AW11: 0 | AX11: 1 | AY11: 1 | AZ11: 1 | BA11: 1 | BV11: 0 | BW11: 0 | BX11: 0 | BY11: 0 | BZ11: 0 | CA11: CE | CB11: Varejo | CC11: Vendedor/Varejo | CF11: 3 | CG11: 3 - Meses | CH11: 0 - S/COMPRA | CI11: 0 - <= 0
A12: M_Capital | B12: 1441 | C12: Roberto | D12: 1018 | G12: CLIENTES | H12: C00475 | I12: PONTO DO LANCHE (JARD FLUMINENSE) | J12: DOURA NASCIMENTO DE ALMEIDA | K12: 24 | M12: 7 | N12: PEQUENO VAREJO | O12: C | P12: Y | Q12: JARDIM FLUMINENSE | R12: FORTALEZA | S12: CE | T12: BR | U12: 45688 | X12: Sex | Y12: Q2 | AA12: Revenda | AB12: 10 dias | AC12: BLT-SANT 804-1 | AD12: CAPITAL CE | AE12: 60734-100 | AF12: -3.815073 | AG12: -38.603461 | AH12: Sim | AI12: Não | AJ12: Não | AK12: 0 | AL12: 800 | AM12: 1 | AN12: 0 | AO12: 1 | AP12: 0 | AQ12: 0 | AR12: 0 | AS12: 0 | AT12: 0 | AU12: 0 | AV12: 0 | AW12: 0 | AX12: 1 | AY12: 1 | AZ12: 1 | BA12: 1 | BB12: 600 | BC12: 600 | BD12: 600 | BE12: 600 | BF12: 0 | BG12: 0 | BH12: 0 | BI12: 0 | BJ12: 1 | BK12: 1 | BL12: 1 | BM12: 1 | BN12: 0 | BO12: 0 | BP12: 0 | BQ12: 0 | BR12: 0 | BS12: 0 | BT12: 0 | BU12: 0 | BV12: 0 | BW12: 0 | BX12: 0 | BY12: 0 | BZ12: 0 | CA12: CE | CB12: Varejo | CC12: Vendedor/Varejo | CD12: -3815073 | CE12: -38603461 | CF12: 3 | CG12: 3 - Meses | CH12: 0 - S/COMPRA | CI12: 0 - <= 0
A13: M_Capital | B13: 1441 | C13: Roberto | D13: 1018 | G13: CLIENTES | H13: C00484 | I13: CHURRASCARIA E PIZZARIA RECANTO DA PICANHA | J13: ANTONIA LUCIA DA COSTA SOUSA | K13: 31 | M13: 10 | N13: INATIVO | O13: C | P13: Y | Q13: ACARACUZINHO | R13: Maracanaú | S13: CE | T13: BR | U13: 45688 | X13: Sex | Y13: Q1 | AA13: Revenda | AB13: 5 dias | AC13: BLT-ITAÚ 130681 | AD13: CAPITAL CE | AE13: 61936-110 | AF13: -3.8484055 | AG13: -38.6168176 | AH13: Sim | AI13: Não | AJ13: Sim | AK13: 0 | AL13: 1200 | AM13: 0 | AN13: 0 | AO13: 0 | AP13: 0 | AQ13: 0 | AR13: 0 | AS13: 0 | AT13: 0 | AU13: 0 | AV13: 0 | AW13: 0 | AX13: 1 | AY13: 1 | AZ13: 1 | BA13: 1 | BV13: 0 | BW13: 0 | BX13: 0 | BY13: 0 | BZ13: 0 | CA13: CE | CB13: Varejo | CC13: Vendedor/Varejo | CD13: -38484055 | CE13: -38616817 | CF13: 3 | CG13: 3 - Meses | CH13: 0 - S/COMPRA | CI13: 0 - <= 0
A14: M_Capital | B14: 1441 | C14: Alexsanderson | D14: 1061 | G14: CLIENTES | H14: C00486 | I14: MERCADINHO ABENCOADO 2 | J14: PEDRO ACASIO DE SOUSA FILHO ME | K14: 15 | M14: 7 | N14: PEQUENO VAREJO | O14: C | P14: Y | Q14: MOURA BRASIL(JACARECANGA) | R14: FORTALEZA | S14: CE | T14: BR | U14: 45691 | X14: Ter | Y14: Q1 | AA14: Revenda | AB14: 5 dias | AC14: BLT-ITAÚ 130681 | AD14: CAPITAL CE | AE14: 60010-200 | AF14: -3.7198133 | AG14: -38.5336972 | AH14: Sim | AI14: Não | AJ14: Sim | AK14: 797.27 | AL14: 880 | AM14: 0 | AN14: 0 | AO14: 0 | AP14: 0 | AQ14: 0 | AR14: 0 | AS14: 0 | AT14: 0 | AU14: 0 | AV14: 0 | AW14: 0 | AX14: 1 | AY14: 1 | AZ14: 1 | BA14: 1 | BV14: 0 | BW14: 0 | BX14: 0 | BY14: 0 | BZ14: 0 | CA14: CE | CB14: Varejo | CC14: Vendedor/Varejo | CD14: -37198133 | CE14: -38533697 | CF14: 3 | CG14: 3 - Meses | CH14: 0 - S/COMPRA | CI14: 0 - <= 0
A15: M_Nacionais | B15: 12 | C15: Nacionais Cap | D15: 998 | G15: G BARBOSA | H15: C00541 | I15: G BARBOSA (W SOARES) | J15: CENCOSUD BRASIL COM LTDA | K15: 2 | M15: 2 | N15: AUTOSSERVIÇO NACIONAL | O15: C | P15: Y | Q15: Edson Queiroz | R15: Fortaleza | S15: CE | T15: BR | U15: 45688 | X15: Seg | Y15: Semanal | AA15: Revenda | AB15: 45 dias | AC15: DEPOSITO | AD15: AUTOSSERVIÇO CE | AE15: 60811-341 | AF15: -3.773404 | AG15: -38.48167 | AH15: Não | AI15: Não | AJ15: Não | AK15: 3482.82 | AL15: 20000 | AM15: 2 | AN15: 1 | AO15: 3 | AP15: 0 | AQ15: 3119.85 | AR15: 0 | AS15: 0 | AT15: 0 | AU15: 1 | AV15: 0 | AW15: 0 | AX15: 1 | AY15: 1 | AZ15: 1 | BA15: 1 | BB15: 1800 | BC15: 1800 | BD15: 1800 | BE15: 1800 | BF15: 0 | BG15: 1.73325 | BH15: 0 | BI15: 0 | BJ15: 3 | BK15: 3 | BL15: 3 | BM15: 3 | BN15: 0 | BO15: 3 | BP15: 0 | BQ15: 0 | BR15: 0 | BS15: 1 | BT15: 0 | BU15: 0 | BV15: 1039.95 | BW15: 1 | BX15: 0 | BY15: 1 | BZ15: 1 | CA15: CE | CB15: AS | CC15: Promotor | CD15: -3773404 | CE15: -3848167 | CF15: 2 | CG15: 2 - Meses | CH15: 4 - BOM | CI15: 4 - < 3000
A16: M_Capital | B16: 1441 | C16: Leonardo | D16: 1007 | G16: CLIENTES | H16: C00579 | I16: MERCADINHO O LOURO (BELA VISTA) | J16: F V DE AMORIM ME | K16: 15 | M16: 7 | N16: PEQUENO VAREJO | O16: C | P16: Y | Q16: BELA VISTA | R16: FORTALEZA | S16: CE | T16: BR | U16: 45688 | X16: Sex | Y16: Q1 | AA16: Revenda | AB16: 14 dias | AC16: BLT-SOF | AD16: CAPITAL CE | AE16: 60441-385 | AF16: -3.7510683 | AG16: -38.5630467 | AH16: Sim | AI16: Não | AJ16: Não | AK16: 0 | AL16: 700 | AM16: 0 | AN16: 0 | AO16: 0 | AP16: 0 | AQ16: 0 | AR16: 0 | AS16: 0 | AT16: 0 | AU16: 0 | AV16: 0 | AW16: 0 | AX16: 1 | AY16: 1 | AZ16: 1 | BA16: 1 | BV16: 0 | BW16: 0 | BX16: 0 | BY16: 0 | BZ16: 0 | CA16: CE | CB16: Varejo | CC16: Vendedor/Varejo | CD16: -37510683 | CE16: -38563046 | CF16: 3 | CG16: 3 - Meses | CH16: 0 - S/COMPRA | CI16: 0 - <= 0
A17: F_Sobral | B17: 2465 | C17: Adriano | D17: 993 | G17: CLIENTES | H17: C00611 | I17: MERCANTIL GERRY | J17: GERRY ADRIANY DE SOUSA ME | K17: 15 | M17: 7 | N17: PEQUENO VAREJO | O17: C | P17: Y | Q17: SAO SEBASTIAO | R17: ITAPIPOCA | S17: CE | T17: BR | U17: 45688 | X17: Ter | Y17: Semanal | AA17: Revenda | AB17: 15 dias | AC17: BLT-SOF | AD17: INTERIOR CE | AE17: 62508-190 | AF17: -3.503178 | AG17: -39.5802923 | AH17: Sim | AI17: Não | AJ17: Não | AK17: 555.14 | AL17: 0 | AM17: 0 | AN17: 0 | AO17: 0 | AP17: 0 | AQ17: 0 | AR17: 0 | AS17: 0 | AT17: 0 | AU17: 0 | AV17: 0 | AW17: 0 | AX17: 1 | AY17: 1 | AZ17: 1 | BA17: 1 | BV17: 0 | BW17: 0 | BX17: 0 | BY17: 0 | BZ17: 0 | CA17: CE | CB17: Varejo | CC17: Vendedor/Varejo | CD17: -3503178 | CE17: -39580292 | CF17: 3 | CG17: 3 - Meses | CH17: 0 - S/COMPRA | CI17: 0 - <= 0
A18: M_Capital | B18: 1441 | C18: Alexsanderson | D18: 1061 | G18: CLIENTES | H18: C00617 | I18: REVISTARIA JOIA (CENTRO) | J18: JOSE EDMAR CORREIA | K18: 10 | M18: 7 | N18: PEQUENO VAREJO | O18: C | P18: Y | Q18: CENTRO | R18: FORTALEZA | S18: CE | T18: BR | U18: 45691 | X18: Seg | Y18: Q1 | AA18: Revenda | AB18: 13 dias | AC18: BLT-ITAÚ 130681 | AD18: CAPITAL CE | AE18: 60020-030 | AF18: -3.7326888 | AG18: -38.532397 | AH18: Sim | AI18: Não | AJ18: Sim | AK18: 628.22 | AL18: 1200 | AM18: 0 | AN18: 0 | AO18: 0 | AP18: 0 | AQ18: 0 | AR18: 0 | AS18: 0 | AT18: 0 | AU18: 0 | AV18: 0 | AW18: 0 | AX18: 1 | AY18: 1 | AZ18: 1 | BA18: 1 | BV18: 0 | BW18: 0 | BX18: 0 | BY18: 0 | BZ18: 0 | CA18: CE | CB18: Varejo | CC18: Vendedor/Varejo | CD18: -37326888 | CE18: -38532397 | CF18: 3 | CG18: 3 - Meses | CH18: 0 - S/COMPRA | CI18: 0 - <= 0
A19: F_Sobral | B19: 2465 | C19: Gonzarlen | D19: 995 | G19: CLIENTES | H19: C00635 | I19: CHURRASCARIA O CHICO | J19: FRANCISCO ANTONIO RODRIGUES MOREIRA | K19: 22 | M19: 7 | N19: PEQUENO VAREJO | O19: C | P19: Y | Q19: Arruda | R19: Paramoti | S19: CE | T19: BR | U19: 45688 | X19: Qui | Y19: Q1 | AA19: Revenda | AB19: 15 dias | AC19: SMARTCOB | AD19: CAPITAL CE | AE19: 62736-000 | AF19: -4.097849 | AG19: -39.239166 | AH19: Sim | AI19: Não | AJ19: Não | AK19: 1015.42 | AL19: 500 | AM19: 0 | AN19: 0 | AO19: 0 | AP19: 0 | AQ19: 0 | AR19: 0 | AS19: 0 | AT19: 0 | AU19: 0 | AV19: 0 | AW19: 0 | AX19: 1 | AY19: 1 | AZ19: 1 | BA19: 1 | BV19: 0 | BW19: 0 | BX19: 0 | BY19: 0 | BZ19: 0 | CA19: CE | CB19: Varejo | CC19: Vendedor/Varejo | CD19: -4097849 | CE19: -39239166 | CF19: 3 | CG19: 3 - Meses | CH19: 0 - S/COMPRA | CI19: 0 - <= 0
A20: M_Regionais | B20: 707 | C20: Benzelieu | D20: 1000 | G20: UNIFORCA I | H20: C00636 | I20: ISMAEL SUPERMERCADO I | J20: ISMAEL SUPERMERCADO LTDA EPP | K20: 31 | M20: 10 | N20: INATIVO | O20: C | P20: Y | Q20: LAGOA REDONDA | R20: FORTALEZA | S20: CE | T20: BR | U20: 45688 | X20: Ter | Y20: Semanal | Z20: 3 | AA20: Revenda | AB20: 21 dias | AC20: BLT-SANT 804-1 | AD20: AUTOSSERVIÇO CE | AE20: 60831-370 | AF20: -3.8264719 | AG20: -38.4742945 | AH20: Sim | AI20: Não | AJ20: Não | AK20: 0 | AL20: 1500 | AM20: 0 | AN20: 0 | AO20: 0 | AP20: 0 | AQ20: 0 | AR20: 0 | AS20: 0 | AT20: 0 | AU20: 0 | AV20: 0 | AW20: 0 | AX20: 1 | AY20: 1 | AZ20: 1 | BA20: 1 | BV20: 0 | BW20: 0 | BX20: 0 | BY20: 0 | BZ20: 0 | CA20: CE | CB20: AS | CC20: Vendedor/AS | CD20: -38264719 | CE20: -38474294 | CF20: 3 | CG20: 3 - Meses | CH20: 0 - S/COMPRA | CI20: 0 - <= 0
A21: M_Regionais | B21: 707 | C21: Benzelieu | D21: 1000 | G21: UNIFORCA I | H21: C00637 | I21: ISMAEL SUPERMERCADO II | J21: ISMAEL SUPERMERCADO LTDA | K21: 1 | M21: 1 | N21: AUTOSSERVIÇO REGIONAL | O21: C | P21: Y | Q21: ANCURI | R21: Fortaleza | S21: CE | T21: BR | U21: 45688 | X21: Qui | Y21: Semanal | Z21: 3 | AA21: Revenda | AB21: 21 dias | AC21: BLT-ITAÚ 130681 | AD21: AUTOSSERVIÇO CE | AE21: 60973-195 | AF21: -3.85762 | AG21: -38.5023 | AH21: Sim | AI21: Não | AJ21: Não | AK21: 0 | AL21: 2000 | AM21: 0 | AN21: 0 | AO21: 0 | AP21: 0 | AQ21: 0 | AR21: 0 | AS21: 0 | AT21: 0 | AU21: 0 | AV21: 0 | AW21: 0 | AX21: 1 | AY21: 1 | AZ21: 1 | BA21: 1 | BV21: 0 | BW21: 0 | BX21: 0 | BY21: 0 | BZ21: 0 | CA21: CE | CB21: AS | CC21: Vendedor/AS | CD21: -385762 | CE21: -385023 | CF21: 3 | CG21: 3 - Meses | CH21: 0 - S/COMPRA | CI21: 0 - <= 0
A22: F_Sobral | B22: 2465 | C22: Gonzarlen | D22: 995 | G22: CLIENTES | H22: C00659 | I22: FARMA SERTAO CENTRAL | J22: PEDROSA E ALVES LTDA ME | K22: 11 | M22: 7 | N22: PEQUENO VAREJO | O22: C | P22: Y | Q22: Centro | R22: Itatira | S22: CE | T22: BR | U22: 45688 | X22: Ter | Y22: Q1 | AA22: Revenda | AB22: 21 dias | AC22: BLT-ITAÚ 130681 | AD22: INTERIOR CE | AE22: 62620-000 | AF22: -4.526461 | AG22: -39.62051 | AH22: Sim | AI22: Não | AJ22: Sim | AK22: 0 | AL22: 700 | AM22: 0 | AN22: 0 | AO22: 0 | AP22: 0 | AQ22: 0 | AR22: 0 | AS22: 0 | AT22: 0 | AU22: 0 | AV22: 0 | AW22: 0 | AX22: 1 | AY22: 1 | AZ22: 1 | BA22: 1 | BV22: 0 | BW22: 0 | BX22: 0 | BY22: 0 | BZ22: 0 | CA22: CE | CB22: Varejo | CC22: Vendedor/Varejo | CD22: -4526461 | CE22: -3962051 | CF22: 3 | CG22: 3 - Meses | CH22: 0 - S/COMPRA | CI22: 0 - <= 0
A23: M_Capital | B23: 1441 | C23: Felipe | D23: 1010 | G23: CLIENTES | H23: C00660 | I23: MERCADINHO POPIA | J23: LUIZ ANTONIO F VIANA | K23: 15 | M23: 7 | N23: PEQUENO VAREJO | O23: C | P23: Y | Q23: ANTONIO MIGUEL | R23: ITAITINGA | S23: CE | T23: BR | U23: 45688 | X23: Seg | Y23: Q1 | AA23: Revenda | AB23: 10 dias | AC23: BLT-SOF | AD23: CAPITAL CE | AE23: 61880-000 | AF23: -3.9752598 | AG23: -38.5170933 | AH23: Sim | AI23: Não | AJ23: Não | AK23: 731.49 | AL23: 250 | AM23: 0 | AN23: 0 | AO23: 0 | AP23: 0 | AQ23: 0 | AR23: 0 | AS23: 0 | AT23: 0 | AU23: 0 | AV23: 0 | AW23: 0 | AX23: 1 | AY23: 1 | AZ23: 1 | BA23: 1 | BV23: 0 | BW23: 0 | BX23: 0 | BY23: 0 | BZ23: 0 | CA23: CE | CB23: Varejo | CC23: Vendedor/Varejo | CD23: -39752598 | CE23: -38517093 | CF23: 3 | CG23: 3 - Meses | CH23: 0 - S/COMPRA | CI23: 0 - <= 0
A24: M_Capital | B24: 1441 | C24: Caio | D24: 1008 | G24: CLIENTES | H24: C00702 | I24: CHURRASCARIA E PIZZARIA SAO FRANCISCO | J24: FRANCISCO FERREIRA M LANCHONETE ME | K24: 22 | M24: 7 | N24: PEQUENO VAREJO | O24: C | P24: Y | Q24: Icaraí | R24: Caucaia | S24: CE | T24: BR | U24: 45691 | X24: Qua | Y24: Q2 | AA24: Revenda | AB24: avista | AC24: BLT-SOF | AD24: CAPITAL CE | AE24: 61620-340 | AF24: -3.6757542 | AG24: -38.6671365 | AH24: Sim | AI24: Não | AJ24: Sim | AK24: 4731.56 | AL24: 0 | AM24: 1 | AN24: 0 | AO24: 1 | AP24: 1456.66 | AQ24: 0 | AR24: 0 | AS24: 0 | AT24: 1 | AU24: 0 | AV24: 0 | AW24: 0 | AX24: 1 | AY24: 1 | AZ24: 1 | BA24: 1 | BB24: 600 | BC24: 600 | BD24: 600 | BE24: 600 | BF24: 2.4277667 | BG24: 0 | BH24: 0 | BI24: 0 | BJ24: 1 | BK24: 1 | BL24: 1 | BM24: 1 | BN24: 1 | BO24: 0 | BP24: 0 | BQ24: 0 | BR24: 1 | BS24: 0 | BT24: 0 | BU24: 0 | BV24: 485.55333 | BW24: 0 | BX24: 0 | BY24: 0 | BZ24: 0 | CA24: CE | CB24: Varejo | CC24: Vendedor/Varejo | CD24: -36757542 | CE24: -38667136 | CF24: 3 | CG24: 3 - Meses | CH24: 2 - RUIM | CI24: 2 - < 600
A25: M_Nacionais | B25: 12 | C25: Franklin | D25: 1005 | G25: CLIENTES AS | H25: C00711 | I25: MERCADINHO O IRMAO (MARANGUAPE) | J25: COMERCIO VAREJISTA DE ALIMENTOS O IRMAO LTDA | K25: 31 | M25: 10 | N25: INATIVO | O25: C | P25: Y | Q25: CENTRO | R25: MARANGUAPE | S25: CE | T25: BR | U25: 45688 | X25: Ter | Y25: Semanal | AA25: Revenda | AB25: 15 dias | AC25: BLT-ITAÚ 130681 | AD25: AUTOSSERVIÇO CE | AE25: 61940-160 | AF25: -3.8918126 | AG25: -38.683258 | AH25: Sim | AI25: Não | AJ25: Não | AK25: 0 | AL25: 660 | AM25: 0 | AN25: 0 | AO25: 0 | AP25: 0 | AQ25: 0 | AR25: 0 | AS25: 0 | AT25: 0 | AU25: 0 | AV25: 0 | AW25: 0 | AX25: 1 | AY25: 1 | AZ25: 1 | BA25: 1 | BV25: 0 | BW25: 0 | BX25: 0 | BY25: 0 | BZ25: 0 | CA25: CE | CB25: AS | CC25: Vendedor/AS | CD25: -38918126 | CE25: -38683258 | CF25: 3 | CG25: 3 - Meses | CH25: 0 - S/COMPRA | CI25: 0 - <= 0
A26: M_Capital | B26: 1441 | C26: Leonardo | D26: 1007 | G26: CLIENTES | H26: C00739 | I26: PIZZARIA E PASTELARIA MAMAMIA | J26: OZANIRA MENDONCA PARENTE | K26: 24 | M26: 7 | N26: PEQUENO VAREJO | O26: C | P26: Y | Q26: JOAO XXIII | R26: FORTALEZA | S26: CE | T26: BR | U26: 45688 | X26: Sex | Y26: Q1 | AA26: Revenda | AB26: 5 dias | AC26: BLT-ITAÚ 130681 | AD26: CAPITAL CE | AE26: 60525-581 | AF26: -3.7746378 | AG26: -38.5806175 | AH26: Sim | AI26: Não | AJ26: Sim | AK26: 484.88 | AL26: 800 | AM26: 0 | AN26: 0 | AO26: 0 | AP26: 0 | AQ26: 0 | AR26: 0 | AS26: 0 | AT26: 0 | AU26: 0 | AV26: 0 | AW26: 0 | AX26: 1 | AY26: 1 | AZ26: 1 | BA26: 1 | BV26: 0 | BW26: 0 | BX26: 0 | BY26: 0 | BZ26: 0 | CA26: CE | CB26: Varejo | CC26: Vendedor/Varejo | CD26: -37746378 | CE26: -38580617 | CF26: 3 | CG26: 3 - Meses | CH26: 0 - S/COMPRA | CI26: 0 - <= 0
A27: M_Nacionais | B27: 12 | C27: Franklin | D27: 1005 | G27: MAXI REDE | H27: C00749 | I27: SUPERMERCADO CANADA | J27: SUPERMERCADO CANADA LTDA ME | K27: 1 | M27: 1 | N27: AUTOSSERVIÇO REGIONAL | O27: C | P27: Y | Q27: GRANJA PORTUGAL | R27: FORTALEZA | S27: CE | T27: BR | U27: 45688 | X27: Sex | Y27: Semanal | Z27: 5 | AA27: Revenda | AB27: 35 dias | AC27: BLT-SOF | AD27: AUTOSSERVIÇO CE | AE27: 60541-495 | AF27: -3.7779164 | AG27: -38.597836 | AH27: Não | AI27: Não | AJ27: Não | AK27: 0 | AL27: 20000 | AM27: 0 | AN27: 0 | AO27: 0 | AP27: 0 | AQ27: 0 | AR27: 0 | AS27: 0 | AT27: 0 | AU27: 0 | AV27: 0 | AW27: 0 | AX27: 1 | AY27: 1 | AZ27: 1 | BA27: 1 | BV27: 0 | BW27: 0 | BX27: 0 | BY27: 0 | BZ27: 0 | CA27: CE | CB27: AS | CC27: Vendedor/AS | CD27: -37779164 | CE27: -38597836 | CF27: 3 | CG27: 3 - Meses | CH27: 0 - S/COMPRA | CI27: 0 - <= 0
A28: F_Sobral | B28: 2465 | C28: Gonzarlen | D28: 995 | G28: CLIENTES | H28: C00779 | I28: CENTRAL FARMA | J28: FRANCISCO AMILTON L BRITO ME | K28: 11 | M28: 7 | N28: PEQUENO VAREJO | O28: C | P28: Y | Q28: Centro | R28: Madalena | S28: CE | T28: BR | U28: 45688 | X28: Ter | Y28: Q1 | AA28: Revenda | AB28: 21 dias | AC28: BLT-SOF | AD28: INTERIOR CE | AE28: 63860-000 | AF28: -4.8527784 | AG28: -39.5756628 | AH28: Sim | AI28: Não | AJ28: Não | AK28: -1483.78 | AL28: 852 | AM28: 1 | AN28: 0 | AO28: 1 | AP28: 393.08 | AQ28: 1274.68 | AR28: 76 | AS28: 0 | AT28: 1 | AU28: 1 | AV28: 0 | AW28: 0 | AX28: 1 | AY28: 1 | AZ28: 1 | BA28: 1 | BB28: 600 | BC28: 600 | BD28: 600 | BE28: 600 | BF28: 0.65513333 | BG28: 2.1244667 | BH28: 0.12666667 | BI28: 0 | BJ28: 1 | BK28: 1 | BL28: 1 | BM28: 1 | BN28: 0 | BO28: 1 | BP28: 0 | BQ28: 0 | BR28: 0 | BS28: 1 | BT28: 0 | BU28: 0 | BV28: 581.25333 | BW28: 0 | BX28: 0 | BY28: 0 | BZ28: 0 | CA28: CE | CB28: Varejo | CC28: Vendedor/Varejo | CD28: -48527784 | CE28: -39575662 | CF28: 2 | CG28: 2 - Meses | CH28: 2 - RUIM | CI28: 2 - < 600
A29: M_Capital | B29: 1441 | C29: Alexsanderson | D29: 1061 | G29: CLIENTES | H29: C00823 | I29: MERCADINHO RITIMEL | J29: F R S SILVA EPP | K29: 15 | M29: 7 | N29: PEQUENO VAREJO | O29: C | P29: Y | Q29: CAIS DO PORTO | R29: FORTALEZA | S29: CE | T29: BR | U29: 45688 | X29: Sab | Y29: Q2 | AA29: Revenda | AB29: 10 dias | AC29: SMARTCOB | AD29: CAPITAL CE | AE29: 60180-140 | AF29: -3.7137233 | AG29: -38.4651228 | AH29: Sim | AI29: Não | AJ29: Não | AK29: 0 | AL29: 1750 | AM29: 0 | AN29: 0 | AO29: 0 | AP29: 0 | AQ29: 0 | AR29: 0 | AS29: 0 | AT29: 0 | AU29: 0 | AV29: 0 | AW29: 0 | AX29: 1 | AY29: 1 | AZ29: 1 | BA29: 1 | BV29: 0 | BW29: 0 | BX29: 0 | BY29: 0 | BZ29: 0 | CA29: CE | CB29: Varejo | CC29: Vendedor/Varejo | CD29: -37137233 | CE29: -38465122 | CF29: 3 | CG29: 3 - Meses | CH29: 0 - S/COMPRA | CI29: 0 - <= 0
A30: F_Sobral | B30: 2465 | C30: Bruno | D30: 1004 | G30: CLIENTES | H30: C00833 | I30: MERCADINHO CASA BRANCA (ITAREMA) | J30: FRANCISCO FRANCINE DE SANTANA | K30: 15 | M30: 7 | N30: PEQUENO VAREJO | O30: C | P30: Y | Q30: ITAREMA | R30: ITAREMA | S30: CE | T30: BR | U30: 45688 | X30: Ter | Y30: Q1 | AA30: Revenda | AB30: 10 dias | AC30: BLT-SOF | AD30: INTERIOR CE | AE30: 62590-000 | AF30: -2.9203301 | AG30: -39.9204283 | AH30: Sim | AI30: Não | AJ30: Não | AK30: 0 | AL30: 800 | AM30: 0 | AN30: 0 | AO30: 0 | AP30: 0 | AQ30: 0 | AR30: 0 | AS30: 0 | AT30: 0 | AU30: 0 | AV30: 0 | AW30: 0 | AX30: 1 | AY30: 1 | AZ30: 1 | BA30: 1 | BV30: 0 | BW30: 0 | BX30: 0 | BY30: 0 | BZ30: 0 | CA30: CE | CB30: Varejo | CC30: Vendedor/Varejo | CD30: -29203301 | CE30: -39920428 | CF30: 3 | CG30: 3 - Meses | CH30: 0 - S/COMPRA | CI30: 0 - <= 0
A31: F_Mossoró | B31: 12 | C31: Melo Monteiro | D31: 1030 | G31: CLIENTES | H31: C00847 | I31: MERCADINHO FORTINHO DA BARRA | J31: LAZARO JUNIOR MEDEIROS DE MELO | K31: 15 | M31: 7 | N31: PEQUENO VAREJO | O31: C | P31: Y | Q31: Centro | R31: Fortim | S31: CE | T31: BR | U31: 45688 | X31: Ter | Y31: Q2 | AA31: Revenda | AB31: 13 dias | AC31: BLT-ITAÚ 130681 | AD31: CAPITAL CE | AE31: 62815-000 | AF31: -4.4326943 | AG31: -37.7821695 | AH31: Sim | AI31: Não | AJ31: Sim | AK31: 0 | AL31: 700 | AM31: 0 | AN31: 0 | AO31: 0 | AP31: 0 | AQ31: 0 | AR31: 0 | AS31: 0 | AT31: 0 | AU31: 0 | AV31: 0 | AW31: 0 | AX31: 1 | AY31: 1 | AZ31: 1 | BA31: 1 | BV31: 0 | BW31: 0 | BX31: 0 | BY31: 0 | BZ31: 0 | CA31: CE | CB31: AS | CC31: Vendedor/AS | CF31: 3 | CG31: 3 - Meses | CH31: 0 - S/COMPRA | CI31: 0 - <= 0
A32: F_Sobral | B32: 2465 | C32: Gonzarlen | D32: 995 | G32: CLIENTES | H32: C00856 | I32: MERCADINHO EDMAR (CAMPOS BELO) | J32: MERCADINHO EDMAR RUFINO LTDA | K32: 15 | M32: 7 | N32: PEQUENO VAREJO | O32: C | P32: Y | Q32: INHUPORANGA | R32: CARIDADE | S32: CE | T32: BR | U32: 45688 | X32: Sex | Y32: Q1 | AA32: Revenda | AB32: 13 dias | AC32: SMARTCOB | AD32: INTERIOR CE | AE32: 62730-000 | AF32: -4.097644 | AG32: -39.0539816 | AH32: Sim | AI32: Não | AJ32: Não | AK32: 0 | AL32: 800 | AM32: 0 | AN32: 0 | AO32: 0 | AP32: 0 | AQ32: 0 | AR32: 0 | AS32: 0 | AT32: 0 | AU32: 0 | AV32: 0 | AW32: 0 | AX32: 1 | AY32: 1 | AZ32: 1 | BA32: 1 | BV32: 0 | BW32: 0 | BX32: 0 | BY32: 0 | BZ32: 0 | CA32: CE | CB32: Varejo | CC32: Vendedor/Varejo | CD32: -4097644 | CE32: -39053981 | CF32: 3 | CG32: 3 - Meses | CH32: 0 - S/COMPRA | CI32: 0 - <= 0
A33: F_Sobral | B33: 2465 | C33: Gonzarlen | D33: 995 | G33: CLIENTES | H33: C00866 | I33: SUPERMERCADO FAMILIA | J33: SUPERMERCADO JG LTDA | K33: 1 | M33: 1 | N33: AUTOSSERVIÇO REGIONAL | O33: C | P33: Y | Q33: Centro | R33: REDENÇÃO | S33: CE | T33: BR | U33: 45688 | X33: Seg | Y33: Q1 | AA33: Revenda | AB33: 21 dias | AC33: SMARTCOB | AD33: INTERIOR CE | AE33: 62790-000 | AF33: -4.22256 | AG33: -38.730234 | AH33: Sim | AI33: Não | AJ33: Sim | AK33: 0 | AL33: 700 | AM33: 0 | AN33: 0 | AO33: 0 | AP33: 0 | AQ33: 0 | AR33: 0 | AS33: 0 | AT33: 0 | AU33: 0 | AV33: 0 | AW33: 0 | AX33: 1 | AY33: 1 | AZ33: 1 | BA33: 1 | BV33: 0 | BW33: 0 | BX33: 0 | BY33: 0 | BZ33: 0 | CA33: CE | CB33: Varejo | CC33: Vendedor/Varejo | CD33: -422256 | CE33: -38730234 | CF33: 3 | CG33: 3 - Meses | CH33: 0 - S/COMPRA | CI33: 0 - <= 0
A34: F_Mossoró | B34: 12 | C34: Melo Monteiro | D34: 1030 | G34: CLIENTES | H34: C00933 | I34: CHURASCARIA FRANGO DOURADO | J34: FRANCISCO GOMES S CHURRASCARIA ME | K34: 22 | M34: 7 | N34: PEQUENO VAREJO | O34: C | P34: Y | Q34: Centro | R34: Aracati | S34: CE | T34: BR | U34: 45688 | X34: Ter | Y34: Q2 | AA34: Revenda | AB34: 13 dias | AC34: SMARTCOB | AD34: INTERIOR CE | AE34: 62800-000 | AF34: -4.5659645 | AG34: -37.7716021 | AH34: Sim | AI34: Não | AJ34: Não | AK34: 688.97 | AL34: 5513 | AM34: 0 | AN34: 0 | AO34: 0 | AP34: 0 | AQ34: 0 | AR34: 0 | AS34: 0 | AT34: 0 | AU34: 0 | AV34: 0 | AW34: 0 | AX34: 1 | AY34: 1 | AZ34: 1 | BA34: 1 | BV34: 0 | BW34: 0 | BX34: 0 | BY34: 0 | BZ34: 0 | CA34: CE | CB34: AS | CC34: Vendedor/AS | CD34: -45659645 | CE34: -37771602 | CF34: 3 | CG34: 3 - Meses | CH34: 0 - S/COMPRA | CI34: 0 - <= 0
A35: F_Sobral | B35: 2465 | C35: Gonzarlen | D35: 995 | G35: CLIENTES | H35: C00973 | I35: MERCADINHO NOSSA SENHORA DE FATIMA | J35: M JAILZA BARROS ROBERTO ME MICROEMPRESA | K35: 15 | M35: 7 | N35: PEQUENO VAREJO | O35: C | P35: Y | Q35: Campos Belos | R35: Caridade | S35: CE | T35: BR | U35: 45688 | X35: Qui | Y35: Q1 | AA35: Revenda | AB35: 5 dias | AC35: BLT-SOF | AD35: INTERIOR CE | AE35: 62730-000 | AF35: -4.094675 | AG35: -39.056715 | AH35: Sim | AI35: Não | AJ35: Sim | AK35: 0 | AL35: 700 | AM35: 1 | AN35: 0 | AO35: 1 | AP35: 0 | AQ35: 0 | AR35: 0 | AS35: 0 | AT35: 0 | AU35: 0 | AV35: 0 | AW35: 0 | AX35: 1 | AY35: 1 | AZ35: 1 | BA35: 1 | BB35: 600 | BC35: 600 | BD35: 600 | BE35: 600 | BF35: 0 | BG35: 0 | BH35: 0 | BI35: 0 | BJ35: 1 | BK35: 1 | BL35: 1 | BM35: 1 | BN35: 0 | BO35: 0 | BP35: 0 | BQ35: 0 | BR35: 0 | BS35: 0 | BT35: 0 | BU35: 0 | BV35: 0 | BW35: 0 | BX35: 0 | BY35: 0 | BZ35: 0 | CA35: CE | CB35: Varejo | CC35: Vendedor/Varejo | CD35: -4094675 | CE35: -39056715 | CF35: 3 | CG35: 3 - Meses | CH35: 0 - S/COMPRA | CI35: 0 - <= 0
A36: F_Sobral | B36: 2465 | C36: Gonzarlen | D36: 995 | G36: CLIENTES | H36: C00976 | I36: COMERCIAL NB | J36: ANTONIA NUBIA BIER | K36: 15 | M36: 7 | N36: PEQUENO VAREJO | O36: C | P36: Y | Q36: Centro | R36: Itatira | S36: CE | T36: BR | U36: 45688 | X36: Ter | Y36: Q1 | AA36: Revenda | AB36: 21 dias | AC36: BLT-SOF | AD36: INTERIOR CE | AE36: 62725-000 | AF36: -4.6511293 | AG36: -39.6747671 | AH36: Sim | AI36: Não | AJ36: Sim | AK36: 2422.04 | AL36: 1200 | AM36: 0 | AN36: 0 | AO36: 0 | AP36: 0 | AQ36: 0 | AR36: 0 | AS36: 0 | AT36: 0 | AU36: 0 | AV36: 0 | AW36: 0 | AX36: 1 | AY36: 1 | AZ36: 1 | BA36: 1 | BV36: 0 | BW36: 0 | BX36: 0 | BY36: 0 | BZ36: 0 | CA36: CE | CB36: Varejo | CC36: Vendedor/Varejo | CD36: -46511293 | CE36: -39674767 | CF36: 3 | CG36: 3 - Meses | CH36: 0 - S/COMPRA | CI36: 0 - <= 0
A37: M_Nacionais | B37: 12 | C37: Nacionais Cap | D37: 998 | G37: PAO DE ACUCAR CE | H37: C00983 | I37: PAO DE ACUCAR (SHOPPING ALDEOTA) | J37: CIA BRASILEIRA DE DISTRIBUICAO | K37: 2 | M37: 2 | N37: AUTOSSERVIÇO NACIONAL | O37: C | P37: Y | Q37: Meireles | R37: Fortaleza | S37: CE | T37: BR | U37: 45688 | X37: Seg | Y37: Semanal | Z37: 18 | AA37: Revenda | AB37: 60 dias | AC37: DEPOSITO | AD37: AUTOSSERVIÇO CE | AE37: 60160-230 | AF37: -3.7338948 | AG37: -38.496815 | AH37: Não | AI37: Não | AJ37: Não | AK37: 0 | AL37: 20000 | AM37: 0 | AN37: 0 | AO37: 0 | AP37: 0 | AQ37: 0 | AR37: 0 | AS37: 0 | AT37: 0 | AU37: 0 | AV37: 0 | AW37: 0 | AX37: 1 | AY37: 1 | AZ37: 1 | BA37: 1 | BV37: 0 | BW37: 0 | BX37: 0 | BY37: 0 | BZ37: 0 | CA37: CE | CB37: AS | CC37: Promotor | CD37: -37338948 | CE37: -38496815 | CF37: 3 | CG37: 3 - Meses | CH37: 0 - S/COMPRA | CI37: 0 - <= 0
A38: M_Capital | B38: 1441 | C38: Francineudo | D38: 1013 | G38: CLIENTES | H38: C01008 | I38: MERCADINHO FAMILIA (PINDORETAMA) | J38: MARIA LAURIENE CRUZ SILVA ME | K38: 15 | M38: 7 | N38: PEQUENO VAREJO | O38: C | P38: Y | Q38: Centro | R38: Pindoretama | S38: CE | T38: BR | U38: 45688 | X38: Ter | Y38: Semanal | AA38: Revenda | AB38: 21 dias | AC38: SMARTCOB | AD38: INTERIOR CE | AE38: 62860-000 | AF38: -4.0307411 | AG38: -38.3028113 | AH38: Sim | AI38: Não | AJ38: Sim | AK38: 0 | AL38: 800 | AM38: 0 | AN38: 0 | AO38: 0 | AP38: 0 | AQ38: 0 | AR38: 0 | AS38: 0 | AT38: 0 | AU38: 0 | AV38: 0 | AW38: 0 | AX38: 1 | AY38: 1 | AZ38: 1 | BA38: 1 | BV38: 0 | BW38: 0 | BX38: 0 | BY38: 0 | BZ38: 0 | CA38: CE | CB38: Varejo | CC38: Vendedor/Varejo | CD38: -40307411 | CE38: -38302811 | CF38: 3 | CG38: 3 - Meses | CH38: 0 - S/COMPRA | CI38: 0 - <= 0
A39: M_Capital | B39: 1441 | C39: Francineudo | D39: 1013 | G39: UNIREDE | H39: C01018 | I39: MERCADINHO E DEPOSITO MULTICASA | J39: ROZIMAR S DE CARVALHO ME | K39: 1 | M39: 1 | N39: AUTOSSERVIÇO REGIONAL | O39: C | P39: Y | Q39: Camurim | R39: Cascavel | S39: CE | T39: BR | U39: 45691 | X39: Seg | Y39: Q1 | AA39: Revenda | AB39: 15 dias | AC39: BLT-ITAÚ 130681 | AD39: INTERIOR CE | AE39: 62850-000 | AF39: -4.1328635 | AG39: -38.24709 | AH39: Sim | AI39: Sim | AJ39: Não | AK39: 0 | AL39: 350 | AM39: 1 | AN39: 0 | AO39: 1 | AP39: 0 | AQ39: 0 | AR39: 0 | AS39: 0 | AT39: 0 | AU39: 0 | AV39: 0 | AW39: 0 | AX39: 1 | AY39: 1 | AZ39: 1 | BA39: 1 | BB39: 0 | BC39: 0 | BD39: 0 | BE39: 0 | BV39: 0 | BW39: 0 | BX39: 0 | BY39: 0 | BZ39: 0 | CA39: CE | CB39: Varejo | CC39: Vendedor/Varejo | CD39: -41328635 | CE39: -3824709 | CF39: 3 | CG39: 3 - Meses | CH39: 0 - S/COMPRA | CI39: 0 - <= 0
A40: M_Nacionais | B40: 12 | C40: Franklin | D40: 1005 | G40: CLIENTES | H40: C01020 | I40: MERCADINHO SANTA TEREZINHA | J40: COMERCIAL DE ALIMENTOS SANTA TEREZINHA LTDA | K40: 1 | M40: 1 | N40: AUTOSSERVIÇO REGIONAL | O40: C | P40: Y | Q40: CENTRO | R40: PACAJUS | S40: CE | T40: BR | U40: 45688 | X40: Qua | Y40: Semanal | AA40: Revenda | AB40: 21 dias | AC40: BLT-SANT 804-1 | AD40: AUTOSSERVIÇO CE | AE40: 62870-000 | AF40: -4.174714 | AG40: -38.46939 | AH40: Sim | AI40: Não | AJ40: Não | AK40: 0 | AL40: 1500 | AM40: 0 | AN40: 0 | AO40: 0 | AP40: 0 | AQ40: 0 | AR40: 0 | AS40: 0 | AT40: 0 | AU40: 0 | AV40: 0 | AW40: 0 | AX40: 1 | AY40: 1 | AZ40: 1 | BA40: 1 | BV40: 0 | BW40: 0 | BX40: 0 | BY40: 0 | BZ40: 0 | CA40: CE | CB40: AS | CC40: Vendedor/AS | CD40: -4174714 | CE40: -3846939 | CF40: 3 | CG40: 3 - Meses | CH40: 0 - S/COMPRA | CI40: 0 - <= 0
A41: M_Capital | B41: 1441 | C41: Caio | D41: 1008 | G41: CLIENTES | H41: C01022 | I41: CHURASCARIA ASSIS | J41: FERNANDA ALVES DE OLIVEIRA | K41: 22 | M41: 7 | N41: PEQUENO VAREJO | O41: C | P41: Y | Q41: MARECHAL RONDON | R41: CAUCAIA | S41: CE | T41: BR | U41: 45688 | X41: Qua | Y41: Q1 | AA41: Revenda | AB41: 7 dias | AC41: BLT-ITAÚ 130681 | AD41: CAPITAL CE | AE41: 61652-140 | AF41: -3.7727902 | AG41: -38.62942 | AH41: Sim | AI41: Não | AJ41: Não | AK41: 0 | AL41: 800 | AM41: 0 | AN41: 0 | AO41: 0 | AP41: 0 | AQ41: 0 | AR41: 0 | AS41: 0 | AT41: 0 | AU41: 0 | AV41: 0 | AW41: 0 | AX41: 1 | AY41: 1 | AZ41: 1 | BA41: 1 | BV41: 0 | BW41: 0 | BX41: 0 | BY41: 0 | BZ41: 0 | CA41: CE | CB41: Varejo | CC41: Vendedor/Varejo | CD41: -37727902 | CE41: -3862942 | CF41: 3 | CG41: 3 - Meses | CH41: 0 - S/COMPRA | CI41: 0 - <= 0
A42: M_Regionais | B42: 707 | C42: Benzelieu | D42: 1000 | G42: UNIFORCA I | H42: C01038 | I42: MERCADINHO CESTAO 2 | J42: SUPERMERCADO CESTAO LTDA -ME | K42: 1 | M42: 1 | N42: AUTOSSERVIÇO REGIONAL | O42: C | P42: Y | Q42: PASSARÉ | R42: Fortaleza | S42: CE | T42: BR | U42: 45691 | X42: Seg | Y42: Semanal | Z42: 4 | AA42: Revenda | AB42: 15 dias | AC42: BLT-ITAÚ 130681 | AD42: AUTOSSERVIÇO CE | AE42: 60743-255 | AF42: -3.8164719 | AG42: -38.528678 | AH42: Sim | AI42: Não | AJ42: Não | AK42: 0 | AL42: 1000 | AM42: 0 | AN42: 0 | AO42: 0 | AP42: 0 | AQ42: 0 | AR42: 0 | AS42: 0 | AT42: 0 | AU42: 0 | AV42: 0 | AW42: 0 | AX42: 1 | AY42: 1 | AZ42: 1 | BA42: 1 | BV42: 0 | BW42: 0 | BX42: 0 | BY42: 0 | BZ42: 0 | CA42: CE | CB42: AS | CC42: Vendedor/AS | CD42: -38164719 | CE42: -38528678 | CF42: 3 | CG42: 3 - Meses | CH42: 0 - S/COMPRA | CI42: 0 - <= 0
A43: F_Sobral | B43: 2465 | C43: Adriano | D43: 993 | G43: CLIENTES | H43: C01043 | I43: BALNEARIO ELIENEIDE | J43: MARIA ELEINEIDE DE SOUSA MESQUITA | K43: 23 | M43: 7 | N43: PEQUENO VAREJO | O43: C | P43: Y | Q43: ITACOLOMI | R43: Uruburetama | S43: CE | T43: BR | U43: 45688 | X43: Sex | Y43: Q2 | AA43: Revenda | AB43: 13 dias | AC43: BLT-SOF | AD43: VAREJO - SOBRAL | AE43: 62650-000 | AF43: -3.624221 | AG43: -39.50639 | AH43: Sim | AI43: Não | AJ43: Não | AK43: 0 | AL43: 2000 | AM43: 0 | AN43: 0 | AO43: 0 | AP43: 705.28 | AQ43: 939.88 | AR43: 0 | AS43: 0 | AT43: 1 | AU43: 1 | AV43: 0 | AW43: 0 | AX43: 1 | AY43: 1 | AZ43: 1 | BA43: 1 | BV43: 548.38667 | BW43: 0 | BX43: 0 | BY43: 0 | BZ43: 0 | CA43: CE | CB43: Varejo | CC43: Vendedor/Varejo | CD43: -3624221 | CE43: -3950639 | CF43: 2 | CG43: 2 - Meses | CH43: 2 - RUIM | CI43: 2 - < 600
A44: M_Capital | B44: 1441 | C44: Felipe | D44: 1010 | G44: CLIENTES | H44: C01069 | I44: CHURRASCARIA E PIZZARIA E BRAS E SILVA | J44: FRANCISCA DAS CHAGAS DUARTE ME | K44: 17 | M44: 7 | N44: PEQUENO VAREJO | O44: C | P44: Y | Q44: SAO CRISTOVAO | R44: Fortaleza | S44: CE | T44: BR | U44: 45688 | X44: Sab | Y44: Q2 | AA44: Revenda | AB44: 13 dias | AC44: SMARTCOB | AD44: CAPITAL CE | AE44: 60866-290 | AF44: -3.835212 | AG44: -38.522717 | AH44: Sim | AI44: Não | AJ44: Não | AK44: 0 | AL44: 700 | AM44: 0 | AN44: 0 | AO44: 0 | AP44: 0 | AQ44: 0 | AR44: 0 | AS44: 0 | AT44: 0 | AU44: 0 | AV44: 0 | AW44: 0 | AX44: 1 | AY44: 1 | AZ44: 1 | BA44: 1 | BV44: 0 | BW44: 0 | BX44: 0 | BY44: 0 | BZ44: 0 | CA44: CE | CB44: Varejo | CC44: Vendedor/Varejo | CD44: -3835212 | CE44: -38522717 | CF44: 3 | CG44: 3 - Meses | CH44: 0 - S/COMPRA | CI44: 0 - <= 0
A45: M_Capital | B45: 1441 | C45: Glauber | D45: 1001 | G45: CLIENTES | H45: C01074 | I45: BIG MONSTER (ITAPERI) | J45: FRANCISCA JESSICA GUILHERME BARROS | K45: 24 | M45: 7 | N45: PEQUENO VAREJO | O45: C | P45: Y | Q45: ITAPERI | R45: FORTALEZA | S45: CE | T45: BR | U45: 45691 | X45: Qui | Y45: Q2 | AA45: Revenda | AB45: 7 dias | AC45: BLT-SANT 804-1 | AD45: CAPITAL CE | AE45: 60714-202 | AF45: -3.8097304 | AG45: -38.4624021 | AH45: Sim | AI45: Não | AJ45: Sim | AK45: 0 | AL45: 800 | AM45: 0 | AN45: 0 | AO45: 0 | AP45: 0 | AQ45: 0 | AR45: 0 | AS45: 0 | AT45: 0 | AU45: 0 | AV45: 0 | AW45: 0 | AX45: 1 | AY45: 1 | AZ45: 1 | BA45: 1 | BV45: 0 | BW45: 0 | BX45: 0 | BY45: 0 | BZ45: 0 | CA45: CE | CB45: Varejo | CC45: Vendedor/Varejo | CD45: -38097304 | CE45: -38462402 | CF45: 3 | CG45: 3 - Meses | CH45: 0 - S/COMPRA | CI45: 0 - <= 0
A46: M_Interior | B46: 1464 | C46: Gardel | D46: 994 | G46: CLIENTES | H46: C01102 | I46: ESPIRITO SANTO HOTEL | J46: ROSA BENICIO DA COSTA PEIXOTO | K46: 16 | M46: 7 | N46: PEQUENO VAREJO | O46: C | P46: Y | Q46: CENTRO | R46: LIMOEIRO DO NORTE | S46: CE | T46: BR | U46: 45688 | X46: Sex | Y46: Q2 | Z46: 4 | AA46: Revenda | AB46: 10 dias | AC46: BLT-SANT 804-1 | AD46: INTERIOR CE | AE46: 62930-000 | AF46: -5.1350953 | AG46: -38.095046 | AH46: Sim | AI46: Não | AJ46: Sim | AK46: 0 | AL46: 1500 | AM46: 0 | AN46: 0 | AO46: 0 | AP46: 0 | AQ46: 903.94 | AR46: 0 | AS46: -903.94 | AT46: 0 | AU46: 1 | AV46: 0 | AW46: 0 | AX46: 1 | AY46: 1 | AZ46: 1 | BA46: 1 | BV46: 301.31333 | BW46: 0 | BX46: 0 | BY46: 0 | BZ46: 0 | CA46: CE | CB46: Varejo | CC46: Vendedor/Varejo | CD46: -51350953 | CE46: -38095046 | CF46: 2 | CG46: 2 - Meses | CH46: 2 - RUIM | CI46: 2 - < 600
A47: F_Sobral | B47: 2465 | C47: Gonzarlen | D47: 995 | G47: CLIENTES | H47: C01103 | I47: FARMACIA DROGAGILDO | J47: LUCIA DE FATIMA L DOS SANTOS | K47: 11 | M47: 7 | N47: PEQUENO VAREJO | O47: C | P47: Y | Q47: CENTRO | R47: Itapiúna | S47: CE | T47: BR | U47: 45688 | X47: Sex | Y47: Q2 | AA47: Revenda | AB47: 10 dias | AC47: BLT-ITAÚ 130681 | AD47: INTERIOR CE | AE47: 62740-000 | AF47: -4.562973 | AG47: -38.921093 | AH47: Sim | AI47: Não | AJ47: Não | AK47: 0 | AL47: 350 | AM47: 1 | AN47: 0 | AO47: 1 | AP47: 0 | AQ47: 0 | AR47: 0 | AS47: 0 | AT47: 0 | AU47: 0 | AV47: 0 | AW47: 0 | AX47: 1 | AY47: 1 | AZ47: 1 | BA47: 1 | BB47: 600 | BC47: 600 | BD47: 600 | BE47: 600 | BF47: 0 | BG47: 0 | BH47: 0 | BI47: 0 | BJ47: 1 | BK47: 1 | BL47: 1 | BM47: 1 | BN47: 0 | BO47: 0 | BP47: 0 | BQ47: 0 | BR47: 0 | BS47: 0 | BT47: 0 | BU47: 0 | BV47: 0 | BW47: 0 | BX47: 0 | BY47: 0 | BZ47: 0 | CA47: CE | CB47: Varejo | CC47: Vendedor/Varejo | CD47: -4562973 | CE47: -38921093 | CF47: 3 | CG47: 3 - Meses | CH47: 0 - S/COMPRA | CI47: 0 - <= 0
A48: M_Interior | B48: 1464 | C48: Gardel | D48: 994 | G48: CLIENTES INTERIOR | H48: C01129 | I48: HOTEL MARIANA | J48: MANOEL ZERIVALDO LIMA | K48: 31 | M48: 10 | N48: INATIVO | O48: C | P48: Y | Q48: NOVA MORADA | R48: MORADA NOVA | S48: CE | T48: BR | U48: 45688 | X48: Seg | Y48: Q1 | AA48: Revenda | AB48: 13 dias | AC48: BLT-ITAÚ 130681 | AD48: INTERIOR CE | AE48: 62940-000 | AH48: Sim | AI48: Não | AJ48: Não | AK48: 0 | AL48: 800 | AM48: 0 | AN48: 0 | AO48: 0 | AP48: 0 | AQ48: 0 | AR48: 0 | AS48: 0 | AT48: 0 | AU48: 0 | AV48: 0 | AW48: 0 | AX48: 1 | AY48: 1 | AZ48: 1 | BA48: 1 | BV48: 0 | BW48: 0 | BX48: 0 | BY48: 0 | BZ48: 0 | CA48: CE | CB48: Varejo | CC48: Vendedor/Varejo | CF48: 3 | CG48: 3 - Meses | CH48: 0 - S/COMPRA | CI48: 0 - <= 0
A49: M_Capital | B49: 1441 | C49: Leonardo | D49: 1007 | G49: CLIENTES | H49: C01168 | I49: LANCHONETE IVANIRA | J49: MARIA IVANIRA GOMES DE ARAUJO | K49: 24 | M49: 7 | N49: PEQUENO VAREJO | O49: C | P49: Y | Q49: JOQUEI CLUBE | R49: FORTALEZA | S49: CE | T49: BR | U49: 45692 | X49: Sex | Y49: Q2 | AA49: Revenda | AB49: 07/14 dias | AC49: BLT-ITAÚ 130681 | AD49: CAPITAL CE | AE49: 60510-055 | AF49: -3.772155 | AG49: -38.572952 | AH49: Sim | AI49: Não | AJ49: Sim | AK49: 0 | AL49: 834.35 | AM49: 0 | AN49: 0 | AO49: 0 | AP49: 0 | AQ49: 0 | AR49: 0 | AS49: 0 | AT49: 0 | AU49: 0 | AV49: 0 | AW49: 0 | AX49: 1 | AY49: 1 | AZ49: 1 | BA49: 1 | BV49: 0 | BW49: 0 | BX49: 0 | BY49: 0 | BZ49: 0 | CA49: CE | CB49: Varejo | CC49: Vendedor/Varejo | CD49: -3772155 | CE49: -38572952 | CF49: 3 | CG49: 3 - Meses | CH49: 0 - S/COMPRA | CI49: 0 - <= 0
A50: F_Sobral | B50: 2465 | C50: Adriano | D50: 993 | G50: CLIENTES | H50: C01188 | I50: IVANILDA AZEVEDO BARBOSA | J50: IVANILDA AZEVEDO BARBOSA | K50: 15 | M50: 7 | N50: PEQUENO VAREJO | O50: C | P50: Y | Q50: CENTRO | R50: ITAPIPOCA | S50: CE | T50: BR | U50: 45688 | X50: Ter | Y50: Q2 | AA50: Revenda | AB50: 10 dias | AC50: BLT-SANT 804-1 | AD50: INTERIOR CE | AE50: 62500-000 | AF50: -3.4997036 | AG50: -39.57908 | AH50: Sim | AI50: Não | AJ50: Sim | AK50: 556.23 | AL50: 800 | AM50: 1 | AN50: 0 | AO50: 1 | AP50: 723.89 | AQ50: 0 | AR50: 0 | AS50: 0 | AT50: 1 | AU50: 0 | AV50: 0 | AW50: 0 | AX50: 1 | AY50: 1 | AZ50: 1 | BA50: 1 | BB50: 600 | BC50: 600 | BD50: 600 | BE50: 600 | BF50: 1.2064833 | BG50: 0 | BH50: 0 | BI50: 0 | BJ50: 1 | BK50: 1 | BL50: 1 | BM50: 1 | BN50: 1 | BO50: 0 | BP50: 0 | BQ50: 0 | BR50: 1 | BS50: 0 | BT50: 0 | BU50: 0 | BV50: 241.29667 | BW50: 0 | BX50: 0 | BY50: 0 | BZ50: 0 | CA50: CE | CB50: Varejo | CC50: Vendedor/Varejo | CD50: -34997036 | CE50: -3957908 | CF50: 3 | CG50: 3 - Meses | CH50: 1 - PÉSSIMO | CI50: 1 - < 300
A51: F_Sobral | B51: 2465 | C51: Luiz Andre | D51: 1016 | G51: CLIENTES | H51: C01194 | I51: MERCADINHO FERNANDO I | J51: SUPERMERCADO FERNANDO COM DE ALIM LTDA | K51: 15 | M51: 7 | N51: PEQUENO VAREJO | O51: C | P51: Y | Q51: CENTRO | R51: Tianguá | S51: CE | T51: BR | U51: 45688 | X51: Qui | Y51: Semanal | Z51: 3 | AA51: Revenda | AB51: 21 dias | AC51: BLT-SOF | AD51: INTERIOR CE | AE51: 62320-121 | AF51: -3.7316824 | AG51: -40.9925368 | AH51: Sim | AI51: Não | AJ51: Não | AK51: 0 | AL51: 600 | AM51: 1 | AN51: 1 | AO51: 2 | AP51: 3247.94 | AQ51: 1996.04 | AR51: 0 | AS51: 0 | AT51: 1 | AU51: 1 | AV51: 0 | AW51: 0 | AX51: 1 | AY51: 1 | AZ51: 1 | BA51: 1 | BB51: 1200 | BC51: 1200 | BD51: 1200 | BE51: 1200 | BF51: 2.7066167 | BG51: 1.6633667 | BH51: 0 | BI51: 0 | BJ51: 2 | BK51: 2 | BL51: 2 | BM51: 2 | BN51: 2 | BO51: 2 | BP51: 0 | BQ51: 0 | BR51: 1 | BS51: 1 | BT51: 0 | BU51: 0 | BV51: 1747.9933 | BW51: 0 | BX51: 0 | BY51: 1 | BZ51: 1 | CA51: CE | CB51: Varejo | CC51: Vendedor/Varejo | CD51: -37316824 | CE51: -40992536 | CF51: 2 | CG51: 2 - Meses | CH51: 4 - BOM | CI51: 4 - < 3000
A52: M_Capital | B52: 1441 | C52: Caio | D52: 1008 | G52: CLIENTES | H52: C01197 | I52: CHURRASCARIA MIRAIMA II | J52: FRANCISCO DAS CHAGAS FERREIRA ME | K52: 22 | M52: 7 | N52: PEQUENO VAREJO | O52: C | P52: Y | Q52: NOVA METROPOLE | R52: CAUCAIA | S52: CE | T52: BR | U52: 45688 | X52: Qua | Y52: Q1 | AA52: Revenda | AB52: 13 dias | AC52: BLT-SOF | AD52: CAPITAL CE | AE52: 61658-400 | AF52: -3.7716787 | AG52: -38.6521177 | AH52: Sim | AI52: Não | AJ52: Não | AK52: 4217.13 | AL52: 800 | AM52: 1 | AN52: 0 | AO52: 1 | AP52: 0 | AQ52: 0 | AR52: 0 | AS52: 0 | AT52: 0 | AU52: 0 | AV52: 0 | AW52: 0 | AX52: 1 | AY52: 1 | AZ52: 1 | BA52: 1 | BB52: 600 | BC52: 600 | BD52: 600 | BE52: 600 | BF52: 0 | BG52: 0 | BH52: 0 | BI52: 0 | BJ52: 1 | BK52: 1 | BL52: 1 | BM52: 1 | BN52: 0 | BO52: 0 | BP52: 0 | BQ52: 0 | BR52: 0 | BS52: 0 | BT52: 0 | BU52: 0 | BV52: 0 | BW52: 0 | BX52: 0 | BY52: 0 | BZ52: 0 | CA52: CE | CB52: Varejo | CC52: Vendedor/Varejo | CD52: -37716787 | CE52: -38652117 | CF52: 3 | CG52: 3 - Meses | CH52: 0 - S/COMPRA | CI52: 0 - <= 0
A53: M_Nacionais | B53: 12 | C53: Franklin | D53: 1005 | G53: NOVA REDE | H53: C01217 | I53: MERCADINHO SUPER PORTELA | J53: SUPER PORTELA COMERCIO DE ALIMENTOS ME | K53: 1 | M53: 1 | N53: AUTOSSERVIÇO REGIONAL | O53: C | P53: Y | Q53: PRESIDENTE KENNEDY | R53: FORTALEZA | S53: CE | T53: BR | U53: 45688 | X53: Qua | Y53: Semanal | AA53: Revenda | AB53: 15 dias | AC53: BLT-ITAÚ 130681 | AD53: AUTOSSERVIÇO CE | AE53: 60355-005 | AF53: -3.7308683 | AG53: -38.564716 | AH53: Sim | AI53: Não | AJ53: Não | AK53: 0 | AL53: 500 | AM53: 0 | AN53: 0 | AO53: 0 | AP53: 0 | AQ53: 0 | AR53: 0 | AS53: 0 | AT53: 0 | AU53: 0 | AV53: 0 | AW53: 0 | AX53: 1 | AY53: 1 | AZ53: 1 | BA53: 1 | BV53: 0 | BW53: 0 | BX53: 0 | BY53: 0 | BZ53: 0 | CA53: CE | CB53: AS | CC53: Vendedor/AS | CD53: -37308683 | CE53: -38564716 | CF53: 3 | CG53: 3 - Meses | CH53: 0 - S/COMPRA | CI53: 0 - <= 0
A54: M_Interior | B54: 1464 | C54: Gardel | D54: 994 | G54: CLIENTES OFERTAS | H54: C01238 | I54: DROGARIA SAO LUIZ (LIMOEIRO) | J54: L N MEDICAMENTOS LTDA | K54: 11 | M54: 7 | N54: PEQUENO VAREJO | O54: C | P54: Y | Q54: CENTRO | R54: LIMOEIRO DO NORTE | S54: CE | T54: BR | U54: 45688 | X54: Ter | Y54: Semanal | AA54: Revenda | AB54: 28 dias | AC54: BLT-SOF | AD54: INTERIOR CE | AE54: 62930-000 | AF54: -5.1400166 | AG54: -38.0967394 | AH54: Sim | AI54: Não | AJ54: Não | AK54: 0 | AL54: 2000 | AM54: 0 | AN54: 0 | AO54: 0 | AP54: 0 | AQ54: 0 | AR54: 0 | AS54: 0 | AT54: 0 | AU54: 0 | AV54: 0 | AW54: 0 | AX54: 1 | AY54: 1 | AZ54: 1 | BA54: 1 | BV54: 0 | BW54: 0 | BX54: 0 | BY54: 0 | BZ54: 0 | CA54: CE | CB54: Varejo | CC54: Vendedor/Varejo | CD54: -51400166 | CE54: -38096739 | CF54: 3 | CG54: 3 - Meses | CH54: 0 - S/COMPRA | CI54: 0 - <= 0
A55: Marujinho | B55: 143 | C55: Vitoria | D55: 1044 | G55: DISTRI CAPITAL MARUJ | H55: C01263 | I55: JOATHAM ALVES | J55: PRISCILA EDI | K55: 29 | M55: 6 | N55: DISTRIBUIDORES | O55: C | P55: Y | Q55: ILHA DO RETIRO | R55: RECIFE | S55: PE | T55: BR | U55: 45688 | X55: Qui | Y55: Semanal | AA55: Revenda | AB55: 7 dias | AC55: BLT-ITAÚ 130681 | AD55: MARUJINHO - INTERIOR - DISTRI. | AE55: 50750-560 | AH55: Sim | AI55: Não | AJ55: Não | AK55: 2798 | AL55: 800 | AM55: 0 | AN55: 0 | AO55: 0 | AP55: 0 | AQ55: 0 | AR55: 0 | AS55: 0 | AT55: 0 | AU55: 0 | AV55: 0 | AW55: 0 | AX55: 1 | AY55: 1 | AZ55: 1 | BA55: 1 | BV55: 0 | BW55: 0 | BX55: 0 | BY55: 0 | BZ55: 0 | CA55: TELEVENDAS | CB55: Marujinho | CC55: Vendedor/Marujinho | CF55: 3 | CG55: 3 - Meses | CH55: 0 - S/COMPRA | CI55: 0 - <= 0
A56: F_Sobral | B56: 2465 | C56: Gonzarlen | D56: 995 | G56: FARMACIAS PROGRESSO | H56: C01295 | I56: FARMACIA PROGRESSO (BOA VIAGEM) | J56: VILANIA VITAL BARROS -EPP | K56: 11 | M56: 7 | N56: PEQUENO VAREJO | O56: C | P56: Y | Q56: CENTO | R56: BOA VIAGEM | S56: CE | T56: BR | U56: 45688 | X56: Qua | Y56: Q1 | AA56: Revenda | AB56: 15 dias | AC56: BLT-SOF | AD56: INTERIOR CE | AE56: 63870000 | AF56: -5.1253706 | AG56: -39.7308488 | AH56: Sim | AI56: Não | AJ56: Não | AK56: 0 | AL56: 700 | AM56: 0 | AN56: 0 | AO56: 0 | AP56: 0 | AQ56: 0 | AR56: 0 | AS56: 0 | AT56: 0 | AU56: 0 | AV56: 0 | AW56: 0 | AX56: 1 | AY56: 1 | AZ56: 1 | BA56: 1 | BV56: 0 | BW56: 0 | BX56: 0 | BY56: 0 | BZ56: 0 | CA56: CE | CB56: Varejo | CC56: Vendedor/Varejo | CD56: -51253706 | CE56: -39730848 | CF56: 3 | CG56: 3 - Meses | CH56: 0 - S/COMPRA | CI56: 0 - <= 0
A57: F_Sobral | B57: 2465 | C57: Gonzarlen | D57: 995 | G57: CLIENTES | H57: C01298 | I57: CHURRASCARIA ACONCHEGO | J57: J RODRIGUES PEREIRA RESTAURANTE- ME | K57: 22 | M57: 7 | N57: PEQUENO VAREJO | O57: C | P57: Y | Q57: VARZEA DO CANTO | R57: BOA VIAGEM | S57: CE | T57: BR | U57: 45691 | X57: Qua | Y57: Q1 | AA57: Revenda | AB57: 15 dias | AC57: BLT-SOF | AD57: INTERIOR CE | AE57: 63870-000 | AF57: -5.11734 | AG57: -39.72827 | AH57: Sim | AI57: Não | AJ57: Não | AK57: 0 | AL57: 800 | AM57: 0 | AN57: 0 | AO57: 0 | AP57: 0 | AQ57: 0 | AR57: 0 | AS57: 0 | AT57: 0 | AU57: 0 | AV57: 0 | AW57: 0 | AX57: 1 | AY57: 1 | AZ57: 1 | BA57: 1 | BV57: 0 | BW57: 0 | BX57: 0 | BY57: 0 | BZ57: 0 | CA57: CE | CB57: Varejo | CC57: Vendedor/Varejo | CD57: -511734 | CE57: -3972827 | CF57: 3 | CG57: 3 - Meses | CH57: 0 - S/COMPRA | CI57: 0 - <= 0
A58: F_Sobral | B58: 2465 | C58: Bruno | D58: 1004 | G58: CLIENTES | H58: C01369 | I58: NETO LANCHES | J58: FRANCISCO MAGNO DE OLIVEIRA | K58: 24 | M58: 7 | N58: PEQUENO VAREJO | O58: C | P58: Y | Q58: CENTRO | R58: CRUZ | S58: CE | T58: BR | U58: 45691 | X58: Qua | Y58: Q1 | AA58: Revenda | AB58: 10 dias | AC58: BLT-ITAÚ 130681 | AD58: INTERIOR CE | AE58: 60000-000 | AF58: -2.9172303 | AG58: -40.1735553 | AH58: Sim | AI58: Não | AJ58: Não | AK58: 0 | AL58: 500 | AM58: 1 | AN58: 0 | AO58: 1 | AP58: 347.44 | AQ58: 314.8 | AR58: 0 | AS58: 0 | AT58: 1 | AU58: 1 | AV58: 0 | AW58: 0 | AX58: 1 | AY58: 1 | AZ58: 1 | BA58: 1 | BB58: 600 | BC58: 600 | BD58: 600 | BE58: 600 | BF58: 0.57906667 | BG58: 0.52466667 | BH58: 0 | BI58: 0 | BJ58: 1 | BK58: 1 | BL58: 1 | BM58: 1 | BN58: 0 | BO58: 0 | BP58: 0 | BQ58: 0 | BR58: 0 | BS58: 0 | BT58: 0 | BU58: 0 | BV58: 220.74667 | BW58: 0 | BX58: 0 | BY58: 0 | BZ58: 0 | CA58: CE | CB58: Varejo | CC58: Vendedor/Varejo | CD58: -29172303 | CE58: -40173555 | CF58: 2 | CG58: 2 - Meses | CH58: 1 - PÉSSIMO | CI58: 1 - < 300
A59: M_Capital | B59: 1441 | C59: Felipe | D59: 1010 | G59: CLIENTES | H59: C01378 | I59: MERCADINHO SANTA ANA (PLANALTO ITAPERI) | J59: FRANCISCO JOSE DA SILVEIRA | K59: 15 | M59: 7 | N59: PEQUENO VAREJO | O59: C | P59: Y | Q59: PLANALTO ITAPERI | R59: FORTALEZA | S59: CE | T59: BR | U59: 45691 | X59: Sex | Y59: Q2 | AA59: Revenda | AB59: 5 dias | AC59: BLT-ITAÚ 130681 | AD59: CAPITAL CE | AE59: 60761-360 | AF59: -3.822898 | AG59: -38.552602 | AH59: Sim | AI59: Não | AJ59: Sim | AK59: 0 | AL59: 800 | AM59: 0 | AN59: 0 | AO59: 0 | AP59: 0 | AQ59: 0 | AR59: 0 | AS59: 0 | AT59: 0 | AU59: 0 | AV59: 0 | AW59: 0 | AX59: 1 | AY59: 1 | AZ59: 1 | BA59: 1 | BV59: 0 | BW59: 0 | BX59: 0 | BY59: 0 | BZ59: 0 | CA59: CE | CB59: Varejo | CC59: Vendedor/Varejo | CD59: -3822898 | CE59: -38552602 | CF59: 3 | CG59: 3 - Meses | CH59: 0 - S/COMPRA | CI59: 0 - <= 0
A60: M_Interior | B60: 1464 | C60: Natanael | D60: 1021 | G60: CLIENTES OFERTAS II | H60: C01390 | I60: MERCANTIL CICERO BERTOLDO (QUIXADA) | J60: CICERO BERTOLDO COMERCIAL DE ALIMENTOS LTDA | K60: 15 | M60: 7 | N60: PEQUENO VAREJO | O60: C | P60: Y | Q60: CENTRO | R60: QUIXADÁ | S60: CE | T60: BR | U60: 45691 | X60: Ter | Y60: Q2 | AA60: Revenda | AB60: 14 dias | AC60: SMARTCOB | AD60: INTERIOR CE | AE60: 63900-169 | AF60: -4.9699446 | AG60: -39.0167888 | AH60: Sim | AI60: Não | AJ60: Sim | AK60: 0 | AL60: 2000 | AM60: 0 | AN60: 0 | AO60: 0 | AP60: 0 | AQ60: 0 | AR60: 0 | AS60: 0 | AT60: 0 | AU60: 0 | AV60: 0 | AW60: 0 | AX60: 1 | AY60: 1 | AZ60: 1 | BA60: 1 | BV60: 0 | BW60: 0 | BX60: 0 | BY60: 0 | BZ60: 0 | CA60: CE | CB60: Varejo | CC60: Vendedor/Varejo | CD60: -49699446 | CE60: -39016788 | CF60: 3 | CG60: 3 - Meses | CH60: 0 - S/COMPRA | CI60: 0 - <= 0
A61: M_Nacionais | B61: 12 | C61: Lettelie | D61: 996 | G61: NOVA REDE | H61: C01432 | I61: MERCADINHO O CARLOS | J61: CARLOS ALBERTO LIMA DE ARAUJO ME | K61: 1 | M61: 1 | N61: AUTOSSERVIÇO REGIONAL | O61: C | P61: Y | Q61: JACARECANGA | R61: FORTALEZA | S61: CE | T61: BR | U61: 45691 | X61: Qua | Y61: Semanal | AA61: Revenda | AB61: 15 dias | AC61: BLT-ITAÚ 130681 | AD61: AUTOSSERVIÇO CE | AE61: 60310-310 | AF61: -3.7175486 | AG61: -38.549892 | AH61: Sim | AI61: Não | AJ61: Não | AK61: 0 | AL61: 1500 | AM61: 0 | AN61: 0 | AO61: 0 | AP61: 0 | AQ61: 0 | AR61: 0 | AS61: 0 | AT61: 0 | AU61: 0 | AV61: 0 | AW61: 0 | AX61: 1 | AY61: 1 | AZ61: 1 | BA61: 1 | BV61: 0 | BW61: 0 | BX61: 0 | BY61: 0 | BZ61: 0 | CA61: CE | CB61: AS | CC61: Vendedor/AS | CD61: -37175486 | CE61: -38549892 | CF61: 3 | CG61: 3 - Meses | CH61: 0 - S/COMPRA | CI61: 0 - <= 0
A62: F_Sobral | B62: 2465 | C62: Gonzarlen | D62: 995 | G62: CLIENTES | H62: C01447 | I62: CHURRASCARIA O CAJUEIRO | J62: ANTONIO NEURIDES UCHOA DA SILVA MICROEMPRESA | K62: 22 | M62: 7 | N62: PEQUENO VAREJO | O62: C | P62: Y | Q62: CENTRO | R62: Canindé | S62: CE | T62: BR | U62: 45688 | X62: Seg | Y62: Q2 | AA62: Revenda | AB62: 10 dias | AC62: BLT-ITAÚ 130681 | AD62: INTERIOR CE | AE62: 62700-000 | AF62: -4.3552419 | AG62: -39.3239573 | AH62: Sim | AI62: Não | AJ62: Não | AK62: 0 | AL62: 500 | AM62: 0 | AN62: 0 | AO62: 0 | AP62: 0 | AQ62: 0 | AR62: 0 | AS62: 0 | AT62: 0 | AU62: 0 | AV62: 0 | AW62: 0 | AX62: 1 | AY62: 1 | AZ62: 1 | BA62: 1 | BV62: 0 | BW62: 0 | BX62: 0 | BY62: 0 | BZ62: 0 | CA62: CE | CB62: Varejo | CC62: Vendedor/Varejo | CD62: -43552419 | CE62: -39323957 | CF62: 3 | CG62: 3 - Meses | CH62: 0 - S/COMPRA | CI62: 0 - <= 0
A63: F_Sobral | B63: 2465 | C63: Luiz Andre | D63: 1016 | G63: CLIENTES | H63: C01453 | I63: SUPERMERCADO FERNANDO II | J63: SUPERMERCADO FERNANDO COMERCIAL DE ALIMENTOS LTDA | K63: 1 | M63: 1 | N63: AUTOSSERVIÇO REGIONAL | O63: C | P63: Y | Q63: CENTRO | R63: Tianguá | S63: CE | T63: BR | U63: 45688 | X63: Qui | Y63: Semanal | Z63: 3 | AA63: Revenda | AB63: 21 dias | AC63: BLT-SOF | AD63: INTERIOR CE | AE63: 62320-077 | AF63: -3.7286682 | AG63: -40.99169 | AH63: Sim | AI63: Não | AJ63: Não | AK63: 1136.47 | AL63: 600 | AM63: 0 | AN63: 1 | AO63: 1 | AP63: 2647.48 | AQ63: 0 | AR63: 0 | AS63: 0 | AT63: 1 | AU63: 0 | AV63: 0 | AW63: 0 | AX63: 1 | AY63: 1 | AZ63: 1 | BA63: 1 | BB63: 600 | BC63: 600 | BD63: 600 | BE63: 600 | BF63: 4.4124667 | BG63: 0 | BH63: 0 | BI63: 0 | BJ63: 1 | BK63: 1 | BL63: 1 | BM63: 1 | BN63: 1 | BO63: 0 | BP63: 0 | BQ63: 0 | BR63: 1 | BS63: 0 | BT63: 0 | BU63: 0 | BV63: 882.49333 | BW63: 0 | BX63: 1 | BY63: 1 | BZ63: 1 | CA63: CE | CB63: Varejo | CC63: Vendedor/Varejo | CD63: -37286682 | CE63: -4099169 | CF63: 3 | CG63: 3 - Meses | CH63: 3 - MEDIANO | CI63: 3 - < 1000
A64: M_Regionais | B64: 707 | C64: Rosana | D64: 997 | G64: PARCERIA I | H64: C01479 | I64: SUPER CONQUISTA | J64: D & A COMERCIAL LTDA ME | K64: 1 | M64: 1 | N64: AUTOSSERVIÇO REGIONAL | O64: C | P64: Y | Q64: CONJUNTO CEARA | R64: FORTALEZA | S64: CE | T64: BR | U64: 45688 | X64: Seg | Y64: Semanal | AA64: Revenda | AB64: 21 dias | AC64: BLT-SOF | AD64: AUTOSSERVIÇO CE | AE64: 60533-660 | AF64: -3.7767723 | AG64: -38.619255 | AH64: Sim | AI64: Não | AJ64: Não | AK64: 0 | AL64: 500 | AM64: 0 | AN64: 0 | AO64: 0 | AP64: 0 | AQ64: 0 | AR64: 0 | AS64: 0 | AT64: 0 | AU64: 0 | AV64: 0 | AW64: 0 | AX64: 1 | AY64: 1 | AZ64: 1 | BA64: 1 | BV64: 0 | BW64: 0 | BX64: 0 | BY64: 0 | BZ64: 0 | CA64: CE | CB64: AS | CC64: Vendedor/AS | CD64: -37767723 | CE64: -38619255 | CF64: 3 | CG64: 3 - Meses | CH64: 0 - S/COMPRA | CI64: 0 - <= 0
A65: M_Capital | B65: 1441 | C65: Glauber | D65: 1001 | G65: CLIENTES | H65: C01490 | I65: CHURRASCARIA VERISSIMO (MONTESE) | J65: J S VERISSIMO | K65: 22 | M65: 7 | N65: PEQUENO VAREJO | O65: C | P65: Y | Q65: MONTESE | R65: FORTALEZA | S65: CE | T65: BR | U65: 45688 | X65: Qua | Y65: Q2 | AA65: Revenda | AB65: 7 dias | AC65: BLT-ITAÚ 130681 | AD65: CAPITAL CE | AE65: 60420-470 | AF65: -3.7632225 | AG65: -38.5486634 | AH65: Sim | AI65: Não | AJ65: Sim | AK65: 330.84 | AL65: 800 | AM65: 1 | AN65: 0 | AO65: 1 | AP65: 0 | AQ65: 0 | AR65: 0 | AS65: 0 | AT65: 0 | AU65: 0 | AV65: 0 | AW65: 0 | AX65: 1 | AY65: 1 | AZ65: 1 | BA65: 1 | BB65: 600 | BC65: 600 | BD65: 600 | BE65: 600 | BF65: 0 | BG65: 0 | BH65: 0 | BI65: 0 | BJ65: 1 | BK65: 1 | BL65: 1 | BM65: 1 | BN65: 0 | BO65: 0 | BP65: 0 | BQ65: 0 | BR65: 0 | BS65: 0 | BT65: 0 | BU65: 0 | BV65: 0 | BW65: 0 | BX65: 0 | BY65: 0 | BZ65: 0 | CA65: CE | CB65: Varejo | CC65: Vendedor/Varejo | CD65: -37632225 | CE65: -38548663 | CF65: 3 | CG65: 3 - Meses | CH65: 0 - S/COMPRA | CI65: 0 - <= 0
A66: M_Nacionais | B66: 12 | C66: Lettelie | D66: 996 | G66: COMPRE BEM | H66: C01499 | I66: MERCADINHO SERRA GRANDE | J66: JOAO PAULO XIMENES DE CARVALHO | K66: 15 | M66: 7 | N66: PEQUENO VAREJO | O66: C | P66: Y | Q66: SANTA CECILIA | R66: FORTALEZA | S66: CE | T66: BR | U66: 45747 | X66: Qui | Y66: Semanal | AA66: Revenda | AB66: 15 dias | AC66: BLT-ITAÚ 130681 | AD66: AUTOSSERVIÇO CE | AE66: 60540-210 | AF66: -3.791678 | AG66: -38.61465 | AH66: Sim | AI66: Não | AJ66: Não | AK66: 0 | AL66: 342 | AM66: 0 | AN66: 0 | AO66: 0 | AP66: 0 | AQ66: 0 | AR66: 0 | AS66: 0 | AT66: 0 | AU66: 0 | AV66: 0 | AW66: 0 | AX66: 1 | AY66: 1 | AZ66: 1 | BA66: 1 | BV66: 0 | BW66: 0 | BX66: 0 | BY66: 0 | BZ66: 0 | CA66: CE | CB66: AS | CC66: Vendedor/AS | CD66: -3791678 | CE66: -3861465 | CF66: 3 | CG66: 3 - Meses | CH66: 0 - S/COMPRA | CI66: 0 - <= 0
A67: F_Sobral | B67: 2465 | C67: Gonzarlen | D67: 995 | G67: CLIENTES | H67: C01583 | I67: MERCADINHO SANTA EDWIRGENS (CAPISTRANO) | J67: ANA L ALVES DE FREITAS - ME | K67: 15 | M67: 7 | N67: PEQUENO VAREJO | O67: C | P67: Y | Q67: CENTRO | R67: CAPISTRANO | S67: CE | T67: BR | U67: 45688 | X67: Sex | Y67: Q2 | AA67: Revenda | AB67: 10 dias | AC67: SMARTCOB | AD67: CAPITAL CE | AE67: 62748-000 | AF67: -4.4653237 | AG67: -38.9062192 | AH67: Sim | AI67: Não | AJ67: Sim | AK67: 0 | AL67: 0 | AM67: 0 | AN67: 0 | AO67: 0 | AP67: 0 | AQ67: 0 | AR67: 0 | AS67: 0 | AT67: 0 | AU67: 0 | AV67: 0 | AW67: 0 | AX67: 1 | AY67: 1 | AZ67: 1 | BA67: 1 | BV67: 0 | BW67: 0 | BX67: 0 | BY67: 0 | BZ67: 0 | CA67: CE | CB67: Varejo | CC67: Vendedor/Varejo | CD67: -44653237 | CE67: -38906219 | CF67: 3 | CG67: 3 - Meses | CH67: 0 - S/COMPRA | CI67: 0 - <= 0
A68: M_Capital | B68: 1441 | C68: Glauber | D68: 1001 | G68: CLIENTES | H68: C01594 | I68: LANCHES ANTONIO | J68: ANTONIO RODRIGUES MONTEIRO | K68: 24 | M68: 7 | N68: PEQUENO VAREJO | O68: C | P68: Y | Q68: JOSE BONIFACIO | R68: FORTALEZA | S68: CE | T68: BR | U68: 45691 | X68: Qui | Y68: Q2 | AA68: Revenda | AB68: 5 dias | AC68: BLT-ITAÚ 130681 | AD68: CAPITAL CE | AE68: 60050-101 | AF68: -3.7391869 | AG68: -38.5268443 | AH68: Sim | AI68: Não | AJ68: Sim | AK68: 0 | AL68: 800 | AM68: 0 | AN68: 0 | AO68: 0 | AP68: 0 | AQ68: 0 | AR68: 0 | AS68: 0 | AT68: 0 | AU68: 0 | AV68: 0 | AW68: 0 | AX68: 1 | AY68: 1 | AZ68: 1 | BA68: 1 | BV68: 0 | BW68: 0 | BX68: 0 | BY68: 0 | BZ68: 0 | CA68: CE | CB68: Varejo | CC68: Vendedor/Varejo | CD68: -37391869 | CE68: -38526844 | CF68: 3 | CG68: 3 - Meses | CH68: 0 - S/COMPRA | CI68: 0 - <= 0
A69: M_Capital | B69: 1441 | C69: Francineudo | D69: 1013 | G69: CLIENTES | H69: C01597 | I69: MEG LANCHES | J69: CARLOS ALBERTO BARBOSA CRUZ | K69: 24 | M69: 7 | N69: PEQUENO VAREJO | O69: C | P69: Y | Q69: ZUMBI | R69: HORIZONTE | S69: CE | T69: BR | U69: 45691 | X69: Qui | Y69: Semanal | AA69: Revenda | AB69: 5 dias | AC69: BLT-ITAÚ 130681 | AD69: CAPITAL CE | AE69: 62880-000 | AF69: -4.099173 | AG69: -38.4857 | AH69: Sim | AI69: Não | AJ69: Sim | AK69: 0 | AL69: 600 | AM69: 0 | AN69: 0 | AO69: 0 | AP69: 0 | AQ69: 0 | AR69: 0 | AS69: 0 | AT69: 0 | AU69: 0 | AV69: 0 | AW69: 0 | AX69: 1 | AY69: 1 | AZ69: 1 | BA69: 1 | BV69: 0 | BW69: 0 | BX69: 0 | BY69: 0 | BZ69: 0 | CA69: CE | CB69: Varejo | CC69: Vendedor/Varejo | CD69: -4099173 | CE69: -384857 | CF69: 3 | CG69: 3 - Meses | CH69: 0 - S/COMPRA | CI69: 0 - <= 0
A70: M_Capital | B70: 1441 | C70: Leonardo | D70: 1007 | G70: FARMACIA AGUIAR | H70: C01604 | I70: FARMACIA AGUIAR (QUINTINO CUNHA) | J70: FARMACIA LIDIANA LTDA ME | K70: 31 | M70: 10 | N70: INATIVO | O70: C | P70: Y | Q70: QUINTINO CUNHA | R70: FORTALEZA | S70: CE | T70: BR | U70: 45688 | X70: Qua | Y70: Q2 | AA70: Revenda | AB70: 15 dias | AC70: BLT-SOF | AD70: CAPITAL CE | AE70: 60352-642 | AF70: -3.7314796 | AG70: -38.599575 | AH70: Sim | AI70: Não | AJ70: Não | AK70: 0 | AL70: 600 | AM70: 0 | AN70: 0 | AO70: 0 | AP70: 0 | AQ70: 0 | AR70: 0 | AS70: 0 | AT70: 0 | AU70: 0 | AV70: 0 | AW70: 0 | AX70: 1 | AY70: 1 | AZ70: 1 | BA70: 1 | BV70: 0 | BW70: 0 | BX70: 0 | BY70: 0 | BZ70: 0 | CA70: CE | CB70: Varejo | CC70: Vendedor/Varejo | CF70: 3 | CG70: 3 - Meses | CH70: 0 - S/COMPRA | CI70: 0 - <= 0
A71: M_Capital | B71: 1441 | C71: Aramys | D71: 1003 | G71: CLIENTES | H71: C01615 | I71: ESQUINA DEMOCRATICA | J71: FRANCISCO JOSE MOREIRA DE CASTRO -ME | K71: 31 | M71: 10 | N71: INATIVO | O71: C | P71: Y | Q71: CENTRO | R71: PARACURU | S71: CE | T71: BR | U71: 45688 | X71: Ter | Y71: Semanal | AA71: Revenda | AB71: 30 dias | AC71: BLT-SOF | AD71: AUTOSSERVIÇO CE | AE71: 62680-000 | AF71: -3.41019 | AG71: -39.02904 | AH71: Sim | AI71: Não | AJ71: Não | AK71: 0 | AL71: 7.2 | AM71: 0 | AN71: 0 | AO71: 0 | AP71: 0 | AQ71: 0 | AR71: 0 | AS71: 0 | AT71: 0 | AU71: 0 | AV71: 0 | AW71: 0 | AX71: 1 | AY71: 1 | AZ71: 1 | BA71: 1 | BV71: 0 | BW71: 0 | BX71: 0 | BY71: 0 | BZ71: 0 | CA71: CE | CB71: Varejo | CC71: Vendedor/Varejo | CF71: 3 | CG71: 3 - Meses | CH71: 0 - S/COMPRA | CI71: 0 - <= 0
A72: Marujinho | B72: 143 | C72: Kellylania | D72: 1043 | G72: VAREJO TLM | H72: C01653 | I72: MERCADINHO LUCINEIDE | J72: LUCINEIDE SANTANA OLIVEIRA | K72: 15 | M72: 7 | N72: PEQUENO VAREJO | O72: C | P72: Y | Q72: CENTRO | R72: ITAREMA | S72: CE | T72: BR | U72: 45688 | X72: Seg | Y72: Q1 | AA72: Revenda | AB72: 8 dias | AC72: BLT-SOF | AD72: ATC MARUJO - SOBRAL | AE72: 62590-000 | AH72: Sim | AI72: Não | AJ72: Não | AK72: 443.93 | AL72: 0 | AM72: 0 | AN72: 0 | AO72: 0 | AP72: 0 | AQ72: 0 | AR72: 0 | AS72: 0 | AT72: 0 | AU72: 0 | AV72: 0 | AW72: 0 | AX72: 1 | AY72: 1 | AZ72: 1 | BA72: 1 | BV72: 0 | BW72: 0 | BX72: 0 | BY72: 0 | BZ72: 0 | CF72: 3 | CG72: 3 - Meses | CH72: 0 - S/COMPRA | CI72: 0 - <= 0
A73: M_Nacionais | B73: 12 | C73: Franklin | D73: 1005 | G73: CLIENTES AS | H73: C01664 | I73: MERCADINHO ADRIEL | J73: MARIA ILEIDE ARRUDA AMORIM MICROEMPRESA | K73: 1 | M73: 1 | N73: AUTOSSERVIÇO REGIONAL | O73: C | P73: Y | Q73: JARDIM IRACEMA | R73: FORTALEZA | S73: CE | T73: BR | U73: 45691 | X73: Qui | Y73: Semanal | AA73: Revenda | AB73: 7 dias | AC73: BLT-SOF | AD73: AUTOSSERVIÇO CE | AE73: 60340-065 | AF73: -3.724086 | AG73: -38.582398 | AH73: Sim | AI73: Não | AJ73: Não | AK73: 0 | AL73: 2000 | AM73: 0 | AN73: 0 | AO73: 0 | AP73: 0 | AQ73: 0 | AR73: 0 | AS73: 0 | AT73: 0 | AU73: 0 | AV73: 0 | AW73: 0 | AX73: 1 | AY73: 1 | AZ73: 1 | BA73: 1 | BV73: 0 | BW73: 0 | BX73: 0 | BY73: 0 | BZ73: 0 | CA73: CE | CB73: AS | CC73: Vendedor/AS | CD73: -3724086 | CE73: -38582398 | CF73: 3 | CG73: 3 - Meses | CH73: 0 - S/COMPRA | CI73: 0 - <= 0
A74: M_Nacionais | B74: 12 | C74: Lettelie | D74: 996 | G74: EXATA | H74: C01669 | I74: SUPERMERCADO O POVO | J74: JOSE GISLEIMAR PONTE ME | K74: 1 | M74: 1 | N74: AUTOSSERVIÇO REGIONAL | O74: C | P74: Y | Q74: RODOLFO TEOFILO | R74: FORTALEZA | S74: CE | T74: BR | U74: 45688 | X74: Qua | Y74: Semanal | AA74: Revenda | AB74: 21 dias | AC74: BLT-SOF | AD74: AUTOSSERVIÇO CE | AE74: 60431-075 | AF74: -3.7413163 | AG74: -38.55161 | AH74: Sim | AI74: Não | AJ74: Sim | AK74: 0 | AL74: 5000 | AM74: 0 | AN74: 0 | AO74: 0 | AP74: 0 | AQ74: 0 | AR74: 0 | AS74: 0 | AT74: 0 | AU74: 0 | AV74: 0 | AW74: 0 | AX74: 1 | AY74: 1 | AZ74: 1 | BA74: 1 | BV74: 0 | BW74: 0 | BX74: 0 | BY74: 0 | BZ74: 0 | CA74: CE | CB74: AS | CC74: Vendedor/AS | CD74: -37413163 | CE74: -3855161 | CF74: 3 | CG74: 3 - Meses | CH74: 0 - S/COMPRA | CI74: 0 - <= 0
A75: M_Capital | B75: 1441 | C75: Leonardo | D75: 1007 | G75: NOVA REDE | H75: C01679 | I75: MERCADINHO DA GENTE (ANT BEZERRA) | J75: FRANCISCO VALTER ARAUJO ARRUDA | K75: 1 | M75: 1 | N75: AUTOSSERVIÇO REGIONAL | O75: C | P75: Y | Q75: ANTONIO BEZERRA | R75: FORTALEZA | S75: CE | T75: BR | U75: 45688 | X75: Qua | Y75: Semanal | AA75: Revenda | AB75: 14 dias | AC75: BLT-SANT 804-1 | AD75: AUTOSSERVIÇO CE | AE75: 60356-320 | AF75: -3.734087 | AG75: -38.582359 | AH75: Sim | AI75: Não | AJ75: Não | AK75: 0 | AL75: 600 | AM75: 0 | AN75: 0 | AO75: 0 | AP75: 0 | AQ75: 0 | AR75: 0 | AS75: 0 | AT75: 0 | AU75: 0 | AV75: 0 | AW75: 0 | AX75: 1 | AY75: 1 | AZ75: 1 | BA75: 1 | BV75: 0 | BW75: 0 | BX75: 0 | BY75: 0 | BZ75: 0 | CA75: CE | CB75: Varejo | CC75: Vendedor/Varejo | CD75: -3734087 | CE75: -38582359 | CF75: 3 | CG75: 3 - Meses | CH75: 0 - S/COMPRA | CI75: 0 - <= 0
A76: Marujinho | B76: 143 | C76: Kellylania | D76: 1043 | G76: DISTRI CAPITAL MARUJ | H76: C01733 | I76: DIST DOUGLAS | J76: RENATO DOUGLAS ARAUJO | K76: 9 | M76: 6 | N76: DISTRIBUIDORES | O76: C | P76: Y | Q76: NOVO PARQUE IRACEMA | R76: MARANGUAPE | S76: CE | T76: BR | U76: 45691 | X76: Sab | Y76: Semanal | AA76: Revenda | AB76: 5 dias | AC76: SPC | AD76: MARUJINHO DIST CAPITAL DUPLICATA | AE76: 61979-000 | AF76: -4.025541 | AG76: -38.870061 | AH76: Sim | AI76: Não | AJ76: Sim | AK76: 48770.96 | AL76: 2230 | AM76: 1 | AN76: 0 | AO76: 1 | AP76: 0 | AQ76: 0 | AR76: 0 | AS76: 0 | AT76: 0 | AU76: 0 | AV76: 0 | AW76: 0 | AX76: 1 | AY76: 1 | AZ76: 1 | BA76: 1 | BB76: 600 | BC76: 600 | BD76: 600 | BE76: 600 | BF76: 0 | BG76: 0 | BH76: 0 | BI76: 0 | BJ76: 1 | BK76: 1 | BL76: 1 | BM76: 1 | BN76: 0 | BO76: 0 | BP76: 0 | BQ76: 0 | BR76: 0 | BS76: 0 | BT76: 0 | BU76: 0 | BV76: 0 | BW76: 0 | BX76: 0 | BY76: 0 | BZ76: 0 | CD76: -4025541 | CE76: -38870061 | CF76: 3 | CG76: 3 - Meses | CH76: 0 - S/COMPRA | CI76: 0 - <= 0
A77: M_Capital | B77: 1441 | C77: Felipe | D77: 1010 | G77: CLIENTES | H77: C01735 | I77: FARMACIA BULA DO REMEDIO | J77: FARMACIA BULA DO REMEDIO LTDA - ME | K77: 11 | M77: 7 | N77: PEQUENO VAREJO | O77: C | P77: Y | Q77: CONJUNTO PALMEIRAS | R77: FORTALEZA | S77: CE | T77: BR | U77: 45688 | X77: Qui | Y77: Q2 | AA77: Revenda | AB77: 15 dias | AC77: BLT-ITAÚ 130681 | AD77: CAPITAL CE | AE77: 60870-020 | AF77: -3.8430711 | AG77: -38.5270134 | AH77: Sim | AI77: Não | AJ77: Não | AK77: 1183.64 | AL77: 800 | AM77: 0 | AN77: 0 | AO77: 0 | AP77: 0 | AQ77: 0 | AR77: 0 | AS77: 0 | AT77: 0 | AU77: 0 | AV77: 0 | AW77: 0 | AX77: 1 | AY77: 1 | AZ77: 1 | BA77: 1 | BV77: 0 | BW77: 0 | BX77: 0 | BY77: 0 | BZ77: 0 | CA77: CE | CB77: Varejo | CC77: Vendedor/Varejo | CD77: -38430711 | CE77: -38527013 | CF77: 3 | CG77: 3 - Meses | CH77: 0 - S/COMPRA | CI77: 0 - <= 0
A78: Marujinho | B78: 143 | C78: Jacilane | D78: 1040 | G78: DISTRI INTERIOR MARU | H78: C01768 | I78: DIST DIOGO (SOBRAL) | J78: DIOGO GUIMARAES PARENTE | K78: 9 | M78: 6 | N78: DISTRIBUIDORES | O78: C | P78: Y | Q78: CENTRO | R78: SOBRAL | S78: CE | T78: BR | U78: 45691 | X78: Sex | Y78: Semanal | AA78: Revenda | AB78: 7 dias | AC78: BLT-SOF | AD78: MARUJINHO DIST INTERIOR DUPLICAT | AE78: 62010160 | AH78: Sim | AI78: Não | AJ78: Sim | AK78: 19384.45 | AL78: 0 | AM78: 3 | AN78: 0 | AO78: 3 | AP78: 0 | AQ78: 0 | AR78: 0 | AS78: 0 | AT78: 0 | AU78: 0 | AV78: 0 | AW78: 0 | AX78: 1 | AY78: 1 | AZ78: 1 | BA78: 1 | BB78: 1800 | BC78: 1800 | BD78: 1800 | BE78: 1800 | BF78: 0 | BG78: 0 | BH78: 0 | BI78: 0 | BJ78: 3 | BK78: 3 | BL78: 3 | BM78: 3 | BN78: 0 | BO78: 0 | BP78: 0 | BQ78: 0 | BR78: 0 | BS78: 0 | BT78: 0 | BU78: 0 | BV78: 0 | BW78: 0 | BX78: 0 | BY78: 0 | BZ78: 0 | CA78: TELEVENDAS | CB78: Marujinho | CC78: Vendedor/Marujinho | CD78: -36841881 | CE78: -40349182 | CF78: 3 | CG78: 3 - Meses | CH78: 0 - S/COMPRA | CI78: 0 - <= 0
A79: M_Interior | B79: 1464 | C79: Natanael | D79: 1021 | G79: CLIENTES | H79: C01791 | I79: DROGARIAS MARTINS | J79: IGOR D B MARTINS ME | K79: 11 | M79: 7 | N79: PEQUENO VAREJO | O79: C | P79: Y | Q79: CARRASCAL | R79: QUIXADÁ | S79: CE | T79: BR | U79: 45688 | X79: Ter | Y79: Semanal | AA79: Revenda | AB79: 5 dias | AC79: BLT-ITAÚ 130681 | AD79: INTERIOR CE | AE79: 63900-000 | AF79: -4.9658085 | AG79: -39.0321001 | AH79: Sim | AI79: Não | AJ79: Sim | AK79: 4632.89 | AL79: 800 | AM79: 0 | AN79: 0 | AO79: 0 | AP79: 0 | AQ79: 0 | AR79: 0 | AS79: 0 | AT79: 0 | AU79: 0 | AV79: 0 | AW79: 0 | AX79: 1 | AY79: 1 | AZ79: 1 | BA79: 1 | BV79: 0 | BW79: 0 | BX79: 0 | BY79: 0 | BZ79: 0 | CA79: CE | CB79: Varejo | CC79: Vendedor/Varejo | CD79: -49658085 | CE79: -390321 | CF79: 3 | CG79: 3 - Meses | CH79: 0 - S/COMPRA | CI79: 0 - <= 0
A80: M_Capital | B80: 1441 | C80: Leonardo | D80: 1007 | G80: CLIENTES | H80: C01802 | I80: CANTINA COLEGIO DOM QUINTINO | J80: RAIMUNDO DIAS VIEIRA MICROEMORESA | K80: 12 | M80: 7 | N80: PEQUENO VAREJO | O80: C | P80: Y | Q80: JARDIM GUANABARA(QUITINO CUNHA) | R80: FORTALEZA | S80: CE | T80: BR | U80: 45691 | X80: Ter | Y80: Q1 | AA80: Revenda | AB80: 14 dias | AC80: BLT-SANT 804-1 | AD80: CAPITAL CE | AE80: 60346-205 | AF80: -3.7403611 | AG80: -38.5895856 | AH80: Sim | AI80: Não | AJ80: Sim | AK80: 0 | AL80: 1000 | AM80: 0 | AN80: 0 | AO80: 0 | AP80: 0 | AQ80: 0 | AR80: 0 | AS80: 0 | AT80: 0 | AU80: 0 | AV80: 0 | AW80: 0 | AX80: 1 | AY80: 1 | AZ80: 1 | BA80: 1 | BV80: 0 | BW80: 0 | BX80: 0 | BY80: 0 | BZ80: 0 | CA80: CE | CB80: Varejo | CC80: Vendedor/Varejo | CD80: -37403611 | CE80: -38589585 | CF80: 3 | CG80: 3 - Meses | CH80: 0 - S/COMPRA | CI80: 0 - <= 0
A81: M_Capital | B81: 1441 | C81: Caio | D81: 1008 | G81: CLIENTES | H81: C01843 | I81: LA FRANTELLI PIZZARIA | J81: LUIS CARLOS PEREIRA DA SILVA | K81: 24 | M81: 7 | N81: PEQUENO VAREJO | O81: C | P81: Y | Q81: PLANALTO CAUCAIA | R81: CAUCAIA | S81: CE | T81: BR | U81: 45688 | X81: Ter | Y81: Q1 | AA81: Revenda | AB81: 5 dias | AC81: BLT-ITAÚ 130681 | AD81: CAPITAL CE | AE81: 61605-500 | AF81: -3.741901 | AG81: -38.664951 | AH81: Sim | AI81: Não | AJ81: Sim | AK81: 375.27 | AL81: 800 | AM81: 1 | AN81: 0 | AO81: 1 | AP81: 336 | AQ81: 0 | AR81: 0 | AS81: 0 | AT81: 1 | AU81: 0 | AV81: 0 | AW81: 0 | AX81: 1 | AY81: 1 | AZ81: 1 | BA81: 1 | BB81: 600 | BC81: 600 | BD81: 600 | BE81: 600 | BF81: 0.56 | BG81: 0 | BH81: 0 | BI81: 0 | BJ81: 1 | BK81: 1 | BL81: 1 | BM81: 1 | BN81: 0 | BO81: 0 | BP81: 0 | BQ81: 0 | BR81: 0 | BS81: 0 | BT81: 0 | BU81: 0 | BV81: 112 | BW81: 0 | BX81: 0 | BY81: 0 | BZ81: 0 | CA81: CE | CB81: Varejo | CC81: Vendedor/Varejo | CD81: -3741901 | CE81: -38664951 | CF81: 3 | CG81: 3 - Meses | CH81: 1 - PÉSSIMO | CI81: 1 - < 300
A82: M_Capital | B82: 1441 | C82: Leonardo | D82: 1007 | G82: CLIENTES | H82: C01865 | I82: LEBLON COMERCIAL DE A & B | J82: LEBLON COMERCIAL DE ALIMENTOS E BEBIDAS LTDA | K82: 15 | M82: 7 | N82: PEQUENO VAREJO | O82: C | P82: Y | Q82: JARDIM GUANABARA | R82: FORTALEZA | S82: CE | T82: BR | U82: 45688 | X82: Qui | Y82: Q2 | AA82: Revenda | AB82: 15 dias | AC82: BLT-ITAÚ 130681 | AD82: CAPITAL CE | AE82: 60346-256 | AF82: -3.7269309 | AG82: -38.589935 | AH82: Sim | AI82: Não | AJ82: Não | AK82: 0 | AL82: 800 | AM82: 0 | AN82: 0 | AO82: 0 | AP82: 0 | AQ82: 0 | AR82: 0 | AS82: 0 | AT82: 0 | AU82: 0 | AV82: 0 | AW82: 0 | AX82: 1 | AY82: 1 | AZ82: 1 | BA82: 1 | BV82: 0 | BW82: 0 | BX82: 0 | BY82: 0 | BZ82: 0 | CA82: CE | CB82: Varejo | CC82: Vendedor/Varejo | CD82: -37269309 | CE82: -38589935 | CF82: 3 | CG82: 3 - Meses | CH82: 0 - S/COMPRA | CI82: 0 - <= 0
A83: M_Regionais | B83: 707 | C83: Rogerio | D83: 1014 | G83: LAGOA | H83: C01872 | I83: LAG ATACADO (BOA VISTA / CASTELAO) | J83: MWN COM DE ALIMENTOS LTDA | K83: 7 | M83: 5 | N83: ATACADO REGIONAL | O83: C | P83: Y | Q83: BOA VISTA / CASTELAO | R83: FORTALEZA | S83: CE | T83: BR | U83: 45688 | X83: Ter | Y83: Semanal | Z83: 5 | AA83: Revenda | AB83: 30 dias | AC83: BLT-SOF | AD83: AUTOSSERVIÇO CE | AE83: 60861-063 | AH83: Não | AI83: Não | AJ83: Não | AK83: 0 | AL83: 20 | AM83: 0 | AN83: 0 | AO83: 0 | AP83: 0 | AQ83: 0 | AR83: 0 | AS83: 0 | AT83: 0 | AU83: 0 | AV83: 0 | AW83: 0 | AX83: 1 | AY83: 1 | AZ83: 1 | BA83: 1 | BV83: 0 | BW83: 0 | BX83: 0 | BY83: 0 | BZ83: 0 | CA83: CE | CB83: AS | CC83: Vendedor/AS | CD83: -38725631 | CE83: -38614544 | CF83: 3 | CG83: 3 - Meses | CH83: 0 - S/COMPRA | CI83: 0 - <= 0
A84: Marujinho | B84: 143 | C84: Kellylania | D84: 1043 | G84: BEBELU | H84: C01943 | I84: BEBELU B72 LIMOEIRO DO NORTE | J84: GOOD ALIMENTOS LTDA ME | K84: 24 | M84: 3 | N84: FOOD SERVICE | O84: C | P84: Y | Q84: CENTRO | R84: LIMOEIRO DO NORTE | S84: CE | T84: BR | U84: 45691 | X84: Sex | Y84: Q1 | AA84: Revenda | AB84: 13 dias | AC84: BLT-SOF | AD84: ATC MARUJO – CAPITAL | AE84: 62930-000 | AF84: -5.146661 | AG84: -38.096584 | AH84: Sim | AI84: Não | AJ84: Sim | AK84: 693.71 | AL84: 0 | AM84: 0 | AN84: 0 | AO84: 0 | AP84: 0 | AQ84: 0 | AR84: 0 | AS84: 0 | AT84: 0 | AU84: 0 | AV84: 0 | AW84: 0 | AX84: 1 | AY84: 1 | AZ84: 1 | BA84: 1 | BV84: 0 | BW84: 0 | BX84: 0 | BY84: 0 | BZ84: 0 | CD84: -5146661 | CE84: -38096584 | CF84: 3 | CG84: 3 - Meses | CH84: 0 - S/COMPRA | CI84: 0 - <= 0
A85: M_Capital | B85: 1441 | C85: Felipe | D85: 1010 | G85: CLIENTES | H85: C01956 | I85: FARMACIA EXATA (EUSEBIO) | J85: SANTOS SILVA & LIMA COM DE PROD FARMA LTDA ME | K85: 11 | M85: 7 | N85: PEQUENO VAREJO | O85: C | P85: Y | Q85: PARQUE HAVAI | R85: EUSÉBIO | S85: CE | T85: BR | U85: 45688 | X85: Qua | Y85: Q1 | AA85: Revenda | AB85: 10 dias | AC85: BLT-SOF | AD85: CAPITAL CE | AE85: 61761-480 | AF85: -3.8928816 | AG85: -38.45622 | AH85: Sim | AI85: Não | AJ85: Sim | AK85: 3693.5 | AL85: 700 | AM85: 0 | AN85: 0 | AO85: 0 | AP85: 0 | AQ85: 0 | AR85: 0 | AS85: 0 | AT85: 0 | AU85: 0 | AV85: 0 | AW85: 0 | AX85: 1 | AY85: 1 | AZ85: 1 | BA85: 1 | BV85: 0 | BW85: 0 | BX85: 0 | BY85: 0 | BZ85: 0 | CA85: CE | CB85: Varejo | CC85: Vendedor/Varejo | CD85: -38928816 | CE85: -3845622 | CF85: 3 | CG85: 3 - Meses | CH85: 0 - S/COMPRA | CI85: 0 - <= 0
A86: M_Capital | B86: 1441 | C86: Caio | D86: 1008 | G86: CLIENTES | H86: C01986 | I86: VAL FARMA | J86: VALMIREIDE ARAGAO RODRIGUES | K86: 11 | M86: 7 | N86: PEQUENO VAREJO | O86: C | P86: Y | Q86: PARQUE POTIRA(JUREMA) | R86: CAUCAIA | S86: CE | T86: BR | U86: 45688 | X86: Seg | Y86: Q2 | AA86: Revenda | AB86: 15 dias | AC86: BLT-SOF | AD86: CAPITAL CE | AE86: 61648-510 | AF86: -3.76122 | AG86: -38.62614 | AH86: Sim | AI86: Não | AJ86: Não | AK86: 0 | AL86: 2000 | AM86: 0 | AN86: 0 | AO86: 0 | AP86: 445.12 | AQ86: 0 | AR86: 0 | AS86: 0 | AT86: 1 | AU86: 0 | AV86: 0 | AW86: 0 | AX86: 1 | AY86: 1 | AZ86: 1 | BA86: 1 | BV86: 148.37333 | BW86: 0 | BX86: 0 | BY86: 0 | BZ86: 0 | CA86: CE | CB86: Varejo | CC86: Vendedor/Varejo | CD86: -376122 | CE86: -3862614 | CF86: 3 | CG86: 3 - Meses | CH86: 1 - PÉSSIMO | CI86: 1 - < 300
A87: M_Nacionais | B87: 12 | C87: Gleiciano | D87: 1006 | G87: INTEGRADA | H87: C02080 | I87: MERCADINHO MARCOS VARIEDADE | J87: ANTONIO MARCOS SILVA FARIAS - ME | K87: 1 | M87: 1 | N87: AUTOSSERVIÇO REGIONAL | O87: C | P87: Y | Q87: SAO CRISTOVAO | R87: FORTALEZA | S87: CE | T87: BR | U87: 45691 | X87: Qui | Y87: Semanal | AA87: Revenda | AB87: 15 dias | AC87: BLT-SOF | AD87: AUTOSSERVIÇO CE | AE87: 60866-290 | AF87: -3.8350475 | AG87: -38.524044 | AH87: Sim | AI87: Não | AJ87: Não | AK87: 0 | AL87: 700 | AM87: 1 | AN87: 0 | AO87: 1 | AP87: 0 | AQ87: 0 | AR87: 0 | AS87: 0 | AT87: 0 | AU87: 0 | AV87: 0 | AW87: 0 | AX87: 1 | AY87: 1 | AZ87: 1 | BA87: 1 | BB87: 600 | BC87: 600 | BD87: 600 | BE87: 600 | BF87: 0 | BG87: 0 | BH87: 0 | BI87: 0 | BJ87: 1 | BK87: 1 | BL87: 1 | BM87: 1 | BN87: 0 | BO87: 0 | BP87: 0 | BQ87: 0 | BR87: 0 | BS87: 0 | BT87: 0 | BU87: 0 | BV87: 0 | BW87: 0 | BX87: 0 | BY87: 0 | BZ87: 0 | CA87: CE | CB87: AS | CC87: Vendedor/AS | CD87: -38350475 | CE87: -38524044 | CF87: 3 | CG87: 3 - Meses | CH87: 0 - S/COMPRA | CI87: 0 - <= 0
A88: F_Sobral | B88: 2465 | C88: Bruno | D88: 1004 | G88: CLIENTES | H88: C02155 | I88: MERCADINHO DOIS IRMAOS | J88: JOSE RENATO SILVEIRA | K88: 15 | M88: 7 | N88: PEQUENO VAREJO | O88: C | P88: Y | Q88: CHAPADINHA | R88: BELA CRUZ | S88: CE | T88: BR | U88: 45691 | X88: Qui | Y88: Q2 | AA88: Revenda | AB88: 14 dias | AC88: SMARTCOB | AD88: INTERIOR CE | AE88: 62570-000 | AF88: -3.0553895 | AG88: -40.1756679 | AH88: Sim | AI88: Não | AJ88: Sim | AK88: 0 | AL88: 700 | AM88: 0 | AN88: 0 | AO88: 0 | AP88: 0 | AQ88: 0 | AR88: 0 | AS88: 0 | AT88: 0 | AU88: 0 | AV88: 0 | AW88: 0 | AX88: 1 | AY88: 1 | AZ88: 1 | BA88: 1 | BV88: 0 | BW88: 0 | BX88: 0 | BY88: 0 | BZ88: 0 | CA88: CE | CB88: Varejo | CC88: Vendedor/Varejo | CD88: -30553895 | CE88: -40175667 | CF88: 3 | CG88: 3 - Meses | CH88: 0 - S/COMPRA | CI88: 0 - <= 0
A89: M_Capital | B89: 1441 | C89: Caio | D89: 1008 | G89: CLIENTES | H89: C02175 | I89: MERCADINHO PONTO CERTO (CANIDEZINHO) | J89: FERNANDO PEREIRA - ME | K89: 1 | M89: 1 | N89: AUTOSSERVIÇO REGIONAL | O89: C | P89: Y | Q89: CANINDEZINHO | R89: FORTALEZA | S89: CE | T89: BR | U89: 45691 | X89: Seg | Y89: Q2 | AA89: Revenda | AB89: 21 dias | AC89: SMARTCOB | AD89: AUTOSSERVIÇO CE | AE89: 60736-130 | AF89: -3.80642 | AG89: -38.610402 | AH89: Sim | AI89: Não | AJ89: Sim | AK89: 340.65 | AL89: 2500 | AM89: 0 | AN89: 0 | AO89: 0 | AP89: 0 | AQ89: 0 | AR89: 0 | AS89: 0 | AT89: 0 | AU89: 0 | AV89: 0 | AW89: 0 | AX89: 1 | AY89: 1 | AZ89: 1 | BA89: 1 | BV89: 0 | BW89: 0 | BX89: 0 | BY89: 0 | BZ89: 0 | CA89: CE | CB89: Varejo | CC89: Vendedor/Varejo | CD89: -380642 | CE89: -38610402 | CF89: 3 | CG89: 3 - Meses | CH89: 0 - S/COMPRA | CI89: 0 - <= 0
A90: M_Capital | B90: 1441 | C90: Glauber | D90: 1001 | G90: CLIENTES | H90: C02188 | I90: BIG MONSTER LOJA 02 (MARAPONGA) | J90: CARLOS ALBERTO DE SOUSA SARAIVA | K90: 24 | M90: 7 | N90: PEQUENO VAREJO | O90: C | P90: Y | Q90: MARAPONGA | R90: FORTALEZA | S90: CE | T90: BR | U90: 45691 | X90: Qua | Y90: Q1 | AA90: Revenda | AB90: 5 dias | AC90: SMARTCOB | AD90: CAPITAL CE | AE90: 60710-001 | AF90: -3.8015823 | AG90: -38.571407 | AH90: Sim | AI90: Não | AJ90: Sim | AK90: -0.03 | AL90: 800 | AM90: 0 | AN90: 0 | AO90: 0 | AP90: 0 | AQ90: 0 | AR90: 0 | AS90: 0 | AT90: 0 | AU90: 0 | AV90: 0 | AW90: 0 | AX90: 1 | AY90: 1 | AZ90: 1 | BA90: 1 | BV90: 0 | BW90: 0 | BX90: 0 | BY90: 0 | BZ90: 0 | CA90: CE | CB90: Varejo | CC90: Vendedor/Varejo | CD90: -38015823 | CE90: -38571407 | CF90: 3 | CG90: 3 - Meses | CH90: 0 - S/COMPRA | CI90: 0 - <= 0
A91: M_Nacionais | B91: 12 | C91: Gleiciano | D91: 1006 | G91: INTEGRADA | H91: C02201 | I91: MERCADINHO E FRIGORIFICO BISTECAO | J91: M S VIANA MELO-ME | K91: 1 | M91: 1 | N91: AUTOSSERVIÇO REGIONAL | O91: C | P91: Y | Q91: Henrique Jorge | R91: FORTALEZA | S91: CE | T91: BR | U91: 45688 | X91: Qui | Y91: Semanal | AA91: Revenda | AB91: 21 dias | AC91: BLT-SOF | AD91: AUTOSSERVIÇO CE | AE91: 60510-290 | AF91: -3.76228 | AG91: -38.58199 | AH91: Sim | AI91: Não | AJ91: Não | AK91: 0 | AL91: 1500 | AM91: 0 | AN91: 0 | AO91: 0 | AP91: 0 | AQ91: 0 | AR91: 0 | AS91: 0 | AT91: 0 | AU91: 0 | AV91: 0 | AW91: 0 | AX91: 1 | AY91: 1 | AZ91: 1 | BA91: 1 | BV91: 0 | BW91: 0 | BX91: 0 | BY91: 0 | BZ91: 0 | CA91: CE | CB91: AS | CC91: Vendedor/AS | CD91: -376228 | CE91: -3858199 | CF91: 3 | CG91: 3 - Meses | CH91: 0 - S/COMPRA | CI91: 0 - <= 0
A92: M_Nacionais | B92: 12 | C92: Franklin | D92: 1005 | G92: CLIENTES | H92: C02211 | I92: MERCADINHO PADRE CICERO MARAPONGA LOJA 1 | J92: CLARA MARIA DE LUCENA ARAUJO | K92: 1 | M92: 1 | N92: AUTOSSERVIÇO REGIONAL | O92: C | P92: Y | Q92: JARDIM CEARENSE | R92: FORTALEZA | S92: CE | T92: BR | U92: 45691 | X92: Qua | Y92: Semanal | AA92: Revenda | AB92: 21 dias | AC92: BLT-SANT 804-1 | AD92: AUTOSSERVIÇO CE | AE92: 60712-055 | AH92: Sim | AI92: Não | AJ92: Não | AK92: -1135.2 | AL92: 1500 | AM92: 1 | AN92: 1 | AO92: 2 | AP92: 0 | AQ92: 0 | AR92: 0 | AS92: 0 | AT92: 0 | AU92: 0 | AV92: 0 | AW92: 0 | AX92: 1 | AY92: 1 | AZ92: 1 | BA92: 1 | BB92: 1200 | BC92: 1200 | BD92: 1200 | BE92: 1200 | BF92: 0 | BG92: 0 | BH92: 0 | BI92: 0 | BJ92: 2 | BK92: 2 | BL92: 2 | BM92: 2 | BN92: 0 | BO92: 0 | BP92: 0 | BQ92: 0 | BR92: 0 | BS92: 0 | BT92: 0 | BU92: 0 | BV92: 0 | BW92: 1 | BX92: 1 | BY92: 1 | BZ92: 1 | CA92: CE | CB92: AS | CC92: Vendedor/AS | CD92: -38049278 | CE92: -385657812 | CF92: 3 | CG92: 3 - Meses | CH92: 0 - S/COMPRA | CI92: 0 - <= 0
A93: F_Sobral | B93: 2465 | C93: Bruno | D93: 1004 | G93: CLIENTES OFERTAS II | H93: C02243 | I93: BRASIL FRIOS | J93: FRIOS FREITAS JIJOCA LTDA | K93: 1 | M93: 1 | N93: AUTOSSERVIÇO REGIONAL | O93: C | P93: Y | Q93: CENTRO | R93: Jijoca de Jericoacoara | S93: CE | T93: BR | U93: 45688 | X93: Sex | Y93: Semanal | AA93: Revenda | AB93: 14/21 dias | AC93: BLT-SOF | AD93: INTERIOR CE | AE93: 62598-970 | AF93: -2.8954905 | AG93: -40.4501193 | AH93: Sim | AI93: Não | AJ93: Não | AK93: 0 | AL93: 700 | AM93: 2 | AN93: 0 | AO93: 2 | AP93: 4057.27 | AQ93: 6762.14 | AR93: 0 | AS93: 0 | AT93: 1 | AU93: 1 | AV93: 0 | AW93: 0 | AX93: 1 | AY93: 1 | AZ93: 1 | BA93: 1 | BB93: 1200 | BC93: 1200 | BD93: 1200 | BE93: 1200 | BF93: 3.3810583 | BG93: 5.6351167 | BH93: 0 | BI93: 0 | BJ93: 2 | BK93: 2 | BL93: 2 | BM93: 2 | BN93: 2 | BO93: 2 | BP93: 0 | BQ93: 0 | BR93: 1 | BS93: 1 | BT93: 0 | BU93: 0 | BV93: 3606.47 | BW93: 0 | BX93: 0 | BY93: 0 | BZ93: 0 | CA93: CE | CB93: Varejo | CC93: Vendedor/Varejo | CD93: -28954905 | CE93: -40450119 | CF93: 2 | CG93: 2 - Meses | CH93: 5 - EXCELENTE | CI93: 5 - < 6000
A94: M_Nacionais | B94: 12 | C94: Lettelie | D94: 996 | G94: EXATA | H94: C02257 | I94: MERCADINHO AVENIDA | J94: M L CAVALCANTE COMERCIO VAREJISTA LTDA ME | K94: 2 | M94: 2 | N94: AUTOSSERVIÇO NACIONAL | O94: C | P94: Y | Q94: MESSEJANA | R94: FORTALEZA | S94: CE | T94: BR | U94: 45747 | X94: Sex | Y94: Semanal | Z94: 6 | AA94: Revenda | AB94: 21 dias | AC94: BLT-ITAÚ 130681 | AD94: AUTOSSERVIÇO CE | AE94: 60841-250 | AH94: Sim | AI94: Não | AJ94: Não | AK94: 0 | AL94: 800 | AM94: 0 | AN94: 0 | AO94: 0 | AP94: 0 | AQ94: 0 | AR94: 0 | AS94: 0 | AT94: 0 | AU94: 0 | AV94: 0 | AW94: 0 | AX94: 1 | AY94: 1 | AZ94: 1 | BA94: 1 | BV94: 0 | BW94: 0 | BX94: 0 | BY94: 0 | BZ94: 0 | CA94: CE | CB94: AS | CC94: Vendedor/AS | CD94: -38245279 | CE94: -384916014 | CF94: 3 | CG94: 3 - Meses | CH94: 0 - S/COMPRA | CI94: 0 - <= 0
A95: M_Capital | B95: 1441 | C95: Aramys | D95: 1003 | G95: CLIENTES | H95: C02313 | I95: MERCADINHO OLIVEIRA | J95: JOSE DE OLIVEIRA FREIRE - ME | K95: 15 | M95: 7 | N95: PEQUENO VAREJO | O95: C | P95: Y | Q95: POVOADO CORREGO FUNDO | R95: TRAIRI | S95: CE | T95: BR | U95: 45688 | X95: Seg | Y95: Q2 | AA95: Revenda | AB95: 10 dias | AC95: BLT-ITAÚ 130681 | AD95: INTERIOR CE | AE95: 62690-000 | AF95: -3.270619 | AG95: -39.27049 | AH95: Sim | AI95: Não | AJ95: Não | AK95: 382.71 | AL95: 700 | AM95: 1 | AN95: 0 | AO95: 1 | AP95: 902.54 | AQ95: 0 | AR95: 0 | AS95: 0 | AT95: 1 | AU95: 0 | AV95: 0 | AW95: 0 | AX95: 1 | AY95: 1 | AZ95: 1 | BA95: 1 | BB95: 600 | BC95: 600 | BD95: 600 | BE95: 600 | BF95: 1.5042333 | BG95: 0 | BH95: 0 | BI95: 0 | BJ95: 1 | BK95: 1 | BL95: 1 | BM95: 1 | BN95: 1 | BO95: 0 | BP95: 0 | BQ95: 0 | BR95: 1 | BS95: 0 | BT95: 0 | BU95: 0 | BV95: 300.84667 | BW95: 0 | BX95: 0 | BY95: 0 | BZ95: 0 | CA95: CE | CB95: Varejo | CC95: Vendedor/Varejo | CD95: -3270619 | CE95: -3927049 | CF95: 3 | CG95: 3 - Meses | CH95: 2 - RUIM | CI95: 2 - < 600
A96: Telemarketing | B96: 143 | C96: Sujeiras TLM | D96: 1025 | G96: CLIENTES | H96: C02379 | I96: VR DISTRIBUIDORA | J96: DIEGO GONCALVES DA COSTA | K96: 031 | M96: 010 | O96: C | P96: Y | Q96: BURITI | R96: ACARAU | S96: CE | T96: BR | U96: 45851 | X96: Ter | Y96: Q2 | AA96: Duplicata | AB96: 14 dias | AC96: BLT-ITAÚ 130681 | AD96: INTERIOR CE | AE96: 62580-000 | AH96: Sim | AI96: Sim | AJ96: Não | AK96: 0 | AL96: 700 | AM96: 0 | AN96: 0 | AO96: 0 | AP96: 0 | AQ96: 0 | AR96: 0 | AS96: 0 | AT96: 0 | AU96: 0 | AV96: 0 | AW96: 0 | AX96: 0 | AY96: 1 | AZ96: 1 | BA96: 1 | BB96: 0 | BC96: 0 | BD96: 0 | BE96: 0 | BV96: 0 | BW96: 0 | BX96: 0 | BY96: 0 | BZ96: 0 | CF96: 3 | CG96: 3 - Meses | CH96: 0 - S/COMPRA | CI96: 0 - <= 0
A97: F_Sobral | B97: 2465 | C97: Luiz Andre | D97: 1016 | G97: CLIENTES | H97: C02402 | I97: MERCADINHO S MEDEIROS | J97: MARIA AURINETE PEREIRA MEDEIROS | K97: 15 | M97: 7 | N97: PEQUENO VAREJO | O97: C | P97: Y | Q97: ANTAO | R97: Tianguá | S97: CE | T97: BR | U97: 45688 | X97: Ter | Y97: Semanal | AA97: Revenda | AB97: 15 dias | AC97: BLT-SOF | AD97: INTERIOR CE | AE97: 62322-045 | AF97: -3.721161 | AG97: -41.004848 | AH97: Sim | AI97: Não | AJ97: Não | AK97: 0 | AL97: 700 | AM97: 0 | AN97: 0 | AO97: 0 | AP97: 0 | AQ97: 0 | AR97: 0 | AS97: 0 | AT97: 0 | AU97: 0 | AV97: 0 | AW97: 0 | AX97: 1 | AY97: 1 | AZ97: 1 | BA97: 1 | BV97: 0 | BW97: 0 | BX97: 0 | BY97: 0 | BZ97: 0 | CA97: CE | CB97: Varejo | CC97: Vendedor/Varejo | CD97: -3721161 | CE97: -41004848 | CF97: 3 | CG97: 3 - Meses | CH97: 0 - S/COMPRA | CI97: 0 - <= 0
A98: F_Sobral | B98: 2465 | C98: Bruno | D98: 1004 | G98: CLIENTES OFERTAS II | H98: C02442 | I98: HOTEL SANTA RITA | J98: PAULO TARSO SILVEIRA ME | K98: 22 | M98: 7 | N98: PEQUENO VAREJO | O98: C | P98: Y | Q98: CENTRO | R98: BELA CRUZ | S98: CE | T98: BR | U98: 45691 | X98: Seg | Y98: Q2 | AA98: Revenda | AB98: 14 dias | AC98: BLT-SANT 804-1 | AD98: INTERIOR CE | AE98: 62570-000 | AF98: -3.0561821 | AG98: -40.1683604 | AH98: Sim | AI98: Não | AJ98: Não | AK98: 0 | AL98: 700 | AM98: 0 | AN98: 0 | AO98: 0 | AP98: 0 | AQ98: 0 | AR98: 0 | AS98: 0 | AT98: 0 | AU98: 0 | AV98: 0 | AW98: 0 | AX98: 1 | AY98: 1 | AZ98: 1 | BA98: 1 | BV98: 0 | BW98: 0 | BX98: 0 | BY98: 0 | BZ98: 0 | CA98: CE | CB98: Varejo | CC98: Vendedor/Varejo | CD98: -30561821 | CE98: -4016836 | CF98: 3 | CG98: 3 - Meses | CH98: 0 - S/COMPRA | CI98: 0 - <= 0
A99: F_Sobral | B99: 2465 | C99: Antonio Pereira | D99: 1012 | G99: CLIENTES OFERTAS | H99: C02485 | I99: MERCADINHO EVIS | J99: FRANCISCO EVILASIO FERREIRA MELO ME | K99: 15 | M99: 7 | N99: PEQUENO VAREJO | O99: C | P99: Y | Q99: ALTO DO CRISTO | R99: SOBRAL | S99: CE | T99: BR | U99: 45688 | X99: Qua | Y99: Q1 | AA99: Revenda | AB99: 15 dias | AC99: BLT-ITAÚ 130681 | AD99: VAREJO - SOBRAL | AE99: 62020-320 | AF99: -3.6892756 | AG99: -40.359461 | AH99: Sim | AI99: Não | AJ99: Não | AK99: 1357.11 | AL99: 700 | AM99: 0 | AN99: 0 | AO99: 0 | AP99: 0 | AQ99: 0 | AR99: 0 | AS99: 0 | AT99: 0 | AU99: 0 | AV99: 0 | AW99: 0 | AX99: 1 | AY99: 1 | AZ99: 1 | BA99: 1 | BV99: 0 | BW99: 0 | BX99: 0 | BY99: 0 | BZ99: 0 | CA99: CE | CB99: Varejo | CC99: Vendedor/Varejo | CD99: -36892756 | CE99: -40359461 | CF99: 3 | CG99: 3 - Meses | CH99: 0 - S/COMPRA | CI99: 0 - <= 0
A100: F_Sobral | B100: 2465 | C100: Bruno | D100: 1004 | G100: CLIENTES | H100: C02494 | I100: BRISA DA TOCA | J100: A DAMASCENO SILVEIRA MERCEARIA - ME | K100: 23 | M100: 7 | N100: PEQUENO VAREJO | O100: C | P100: Y | Q100: ANINGAS | R100: CRUZ | S100: CE | T100: BR | U100: 45691 | X100: Sex | Y100: Semanal | AA100: Revenda | AB100: 14 dias | AC100: BLT-SANT 804-1 | AD100: INTERIOR CE | AE100: 62873-000 | AF100: -2.9400221 | AG100: -40.1833213 | AH100: Sim | AI100: Não | AJ100: Não | AK100: 0 | AL100: 700 | AM100: 0 | AN100: 0 | AO100: 0 | AP100: 0 | AQ100: 0 | AR100: 0 | AS100: 0 | AT100: 0 | AU100: 0 | AV100: 0 | AW100: 0 | AX100: 1 | AY100: 1 | AZ100: 1 | BA100: 1 | BV100: 0 | BW100: 0 | BX100: 0 | BY100: 0 | BZ100: 0 | CA100: CE | CB100: Varejo | CC100: Vendedor/Varejo | CD100: -29400221 | CE100: -40183321 | CF100: 3 | CG100: 3 - Meses | CH100: 0 - S/COMPRA | CI100: 0 - <= 0
...

Sheet Resumo Dia
A1: SC_3 meses Diário | B1: 46142
A2: Supervisor | B2: Manhã | C2: Tarde | D2: Diferença
A3: F_Juazeiro | B3: 10 | D3: =C3-B3 -> -10
A4: F_Maranhão | B4: 6 | D4: =C4-B4 -> -6
A5: F_Mossoró | B5: 16 | D5: =C5-B5 -> -16
A6: F_Sobral | B6: 63 | D6: =C6-B6 -> -63
A7: F_Teresina | B7: 33 | D7: =C7-B7 -> -33
A8: M_Capital | B8: 82 | D8: =C8-B8 -> -82
A9: M_Interior | B9: 9 | D9: =C9-B9 -> -9
A10: M_Nacionais | B10: 20 | D10: =C10-B10 -> -20
A11: M_Regionais | B11: 2 | D11: =C11-B11 -> -2
A12: F_Pernambuco_AS | B12: 1 | D12: =C12-B12 -> -1
A13: F_Pernambuco_PB | B13: 5 | D13: =C13-B13 -> -5
A14: F_Pernambuco_VA | B14: 9 | D14: =C14-B14 -> -9
... A16: Telemarketing | B16: 8 | D16: =C16-B16 -> -8
A17: Total Geral | B17: =SUM(B3:B16) -> 275 | C17: =SUM(C3:C16) -> 0 | D17: =B17-C17 -> 275

Sheet Analitico
A1: Supervisor | B1: Total Freezer | C1: Total freezer S/C | D1: % de Freezer S/C dentro de cada equipe | E1: % de participação de cada equipe no PROBLEMA TOTAL
A2: F_Juazeiro | B2: =_xlfn.XLOOKUP(A2,Fotografia!A:A,Fotografia!G:G) -> 240 | C2: 10 | D2: =C2/B2 -> 0.041666667 | E2: =C2/$C$16 -> 0.036363636
A3: F_Maranhão | B3: =_xlfn.XLOOKUP(A3,Fotografia!A:A,Fotografia!G:G) -> 125 | C3: 6 | D3: =C3/B3 -> 0.048 | E3: =C3/$C$16 -> 0.021818182
A4: F_Mossoró | B4: =_xlfn.XLOOKUP(A4,Fotografia!A:A,Fotografia!G:G) -> 57 | C4: 16 | D4: =C4/B4 -> 0.28070175 | E4: =C4/$C$16 -> 0.058181818
A5: F_Pernambuco_AS | B5: =_xlfn.XLOOKUP(A5,Fotografia!A:A,Fotografia!G:G) -> 23 | C5: 1 | D5: =C5/B5 -> 0.043478261 | E5: =C5/$C$16 -> 0.0036363636
A6: F_Pernambuco_PB | B6: =_xlfn.XLOOKUP(A6,Fotografia!A:A,Fotografia!G:G) -> 6 | C6: 5 | D6: =C6/B6 -> 0.83333333 | E6: =C6/$C$16 -> 0.018181818
A7: F_Pernambuco_VA | B7: =_xlfn.XLOOKUP(A7,Fotografia!A:A,Fotografia!G:G) -> 35 | C7: 9 | D7: =C7/B7 -> 0.25714286 | E7: =C7/$C$16 -> 0.032727273
A8: F_Sobral | B8: =_xlfn.XLOOKUP(A8,Fotografia!A:A,Fotografia!G:G) -> 684 | C8: 63 | D8: =C8/B8 -> 0.092105263 | E8: =C8/$C$16 -> 0.22909091
A9: F_Teresina | B9: =_xlfn.XLOOKUP(A9,Fotografia!A:A,Fotografia!G:G) -> 242 | C9: 33 | D9: =C9/B9 -> 0.13636364 | E9: =C9/$C$16 -> 0.12
A10: M_Capital | B10: =_xlfn.XLOOKUP(A10,Fotografia!A:A,Fotografia!G:G) -> 891 | C10: 82 | D10: =C10/B10 -> 0.092031425 | E10: =C10/$C$16 -> 0.29818182
A11: M_Interior | B11: =_xlfn.XLOOKUP(A11,Fotografia!A:A,Fotografia!G:G) -> 183 | C11: 9 | D11: =C11/B11 -> 0.049180328 | E11: =C11/$C$16 -> 0.032727273
A12: M_Nacionais | B12: =_xlfn.XLOOKUP(A12,Fotografia!A:A,Fotografia!G:G) -> 459 | C12: 20 | D12: =C12/B12 -> 0.043572985 | E12: =C12/$C$16 -> 0.072727273
A13: M_Regionais | B13: =_xlfn.XLOOKUP(A13,Fotografia!A:A,Fotografia!G:G) -> 341 | C13: 2 | D13: =C13/B13 -> 0.0058651026 | E13: =C13/$C$16 -> 0.0072727273
... A15: Telemarketing | B15: =_xlfn.XLOOKUP(A15,Fotografia!A:A,Fotografia!G:G) -> 218 | C15: 8 | D15: =C15/B15 -> 0.036697248 | E15: =C15/$C$16 -> 0.029090909
A16: Total | B16: =SUM(B2:B15) -> 3889 | C16: =SUM(C2:C15) -> 275 | D16: =C16/B16 -> 0.070712265 | E16: =C16/$C$16 -> 1
A18: Indicador GERAL (empresa) | B18: =C16/B16 -> 0.070712265
A19: Meta 3 M_SC | B19: 0.01
A20: Meta Mês | B20: 0.1
A22: 0.093
A23: 0.089
